{"data": [{"home_team": "Santa Fe Bogota", "competition_name": "Categoria Primera A", "away_team": "Boyaca Chico", "market": "classic", "competition_cluster": "Colombia", "prediction": "1", "status": "pending", "federation": "CONMEBOL", "is_expired": false, "season": "2025 - Apertura", "id": 352503, "result": "", "start_date": "2025-04-27T20:00:00", "last_update_at": "2025-04-27T01:36:24.710477", "odds": {"1": 1.34, "X": 4.463, "2": 9.075, "1X": 1.053, "X2": 3.008, "12": 1.177}}, {"home_team": "Al-Wahda Abu Dhabi", "competition_name": "Pro-League", "away_team": "Shabab Al-Ahli Dubai", "market": "classic", "competition_cluster": "UAE", "prediction": "2", "status": "pending", "federation": "AFC", "is_expired": false, "season": "2024 - 2025", "id": 352551, "result": "", "start_date": "2025-04-27T17:45:00", "last_update_at": "2025-04-27T01:36:24.710477", "odds": {"1": 3.408, "X": 3.297, "2": 1.945, "1X": 1.723, "X2": 1.27, "12": 1.26}}, {"home_team": "Aucas Quito", "competition_name": "Serie A", "away_team": "Mushuc Runa", "market": "classic", "competition_cluster": "Ecuador", "prediction": "12", "status": "pending", "federation": "CONMEBOL", "is_expired": false, "season": "2025 - First Stage", "id": 352510, "result": "", "start_date": "2025-04-27T19:00:00", "last_update_at": "2025-04-27T01:36:24.710477", "odds": {"1": 1.947, "X": 3.392, "2": 3.595, "1X": 1.242, "X2": 1.787, "12": 1.283}}, {"home_team": "Honefoss", "competition_name": "2. Division", "away_team": "Tromsdalen", "market": "classic", "competition_cluster": "Norway", "prediction": "12", "status": "pending", "federation": "UEFA", "is_expired": false, "season": "2025", "id": 352376, "result": "", "start_date": "2025-04-27T12:00:00", "last_update_at": "2025-04-27T05:41:30.075874", "odds": {"1": 2.678, "X": 3.592, "2": 2.185, "1X": 1.567, "X2": 1.387, "12": 1.223}}, {"home_team": "FC Ufa", "competition_name": "First League", "away_team": "Shinnik Yaroslavl", "market": "classic", "competition_cluster": "Russia", "prediction": "1X", "status": "pending", "federation": "UEFA", "is_expired": false, "season": "2024 - 2025", "id": 352401, "result": "", "start_date": "2025-04-27T12:00:00", "last_update_at": "2025-04-27T05:41:30.075874", "odds": {"1": 2.35, "X": 3.015, "2": 3.115, "1X": 1.325, "X2": 1.53, "12": 1.345}}, {"home_team": "Vaduz", "competition_name": "Challenge League", "away_team": "Etoile Carouge", "market": "classic", "competition_cluster": "Switzerland", "prediction": "12", "status": "pending", "federation": "UEFA", "is_expired": false, "season": "2024 - 2025", "id": 352428, "result": "", "start_date": "2025-04-27T13:15:00", "last_update_at": "2025-04-27T05:41:30.075874", "odds": {"1": 2.632, "X": 3.418, "2": 2.3, "1X": 1.526, "X2": 1.4, "12": 1.27}}, {"home_team": "Follo", "competition_name": "2. Division", "away_team": "Stjordals Blink", "market": "classic", "competition_cluster": "Norway", "prediction": "12", "status": "pending", "federation": "UEFA", "is_expired": false, "season": "2025", "id": 352380, "result": "", "start_date": "2025-04-27T13:30:00", "last_update_at": "2025-04-27T05:41:30.075874", "odds": {"1": 2.455, "X": 3.797, "2": 2.263, "1X": 1.537, "X2": 1.443, "12": 1.207}}, {"home_team": "Kuressaare", "competition_name": "Meistriliiga", "away_team": "Narva Trans", "market": "classic", "competition_cluster": "Estonia", "prediction": "2", "status": "pending", "federation": "UEFA", "is_expired": false, "season": "2025", "id": 352313, "result": "", "start_date": "2025-04-27T15:00:00", "last_update_at": "2025-04-27T05:41:30.075874", "odds": {"1": 3.792, "X": 3.636, "2": 1.76, "1X": 1.925, "X2": 1.205, "12": 1.25}}, {"home_team": "Kolos Kovalivka", "competition_name": "Premier League", "away_team": "Polissya Zhytomyr", "market": "classic", "competition_cluster": "Ukraine", "prediction": "1X", "status": "pending", "federation": "UEFA", "is_expired": false, "season": "2024 - 2025", "id": 352446, "result": "", "start_date": "2025-04-27T13:30:00", "last_update_at": "2025-04-27T05:41:30.075874", "odds": {"1": 2.95, "X": 2.868, "2": 2.543, "1X": 1.47, "X2": 1.367, "12": 1.38}}, {"home_team": "Gornik Zabrze", "competition_name": "Ekstraklasa", "away_team": "Widzew Lodz", "market": "classic", "competition_cluster": "Poland", "prediction": "12", "status": "pending", "federation": "UEFA", "is_expired": false, "season": "2024 - 2025", "id": 352383, "result": "", "start_date": "2025-04-27T13:45:00", "last_update_at": "2025-04-27T05:41:30.075874", "odds": {"1": 1.878, "X": 3.603, "2": 3.872, "1X": 1.235, "X2": 1.888, "12": 1.267}}, {"home_team": "Nafta Lendava", "competition_name": "1. SNL", "away_team": "FC Koper", "market": "classic", "competition_cluster": "Slovenia", "prediction": "2", "status": "pending", "federation": "UEFA", "is_expired": false, "season": "2024 - 2025", "id": 352414, "result": "", "start_date": "2025-04-27T14:00:00", "last_update_at": "2025-04-27T05:41:30.075874", "odds": {"1": 3.62, "X": 3.42, "2": 1.884, "1X": 1.842, "X2": 1.222, "12": 1.275}}, {"home_team": "MTK Budapest", "competition_name": "NB I", "away_team": "Ferencvarosi", "market": "classic", "competition_cluster": "Hungary", "prediction": "2", "status": "pending", "federation": "UEFA", "is_expired": false, "season": "2024 - 2025", "id": 352327, "result": "", "start_date": "2025-04-27T14:30:00", "last_update_at": "2025-04-27T05:41:30.075874", "odds": {"1": 4.978, "X": 4.083, "2": 1.548, "1X": 2.272, "X2": 1.15, "12": 1.202}}, {"home_team": "Villarreal", "competition_name": "Primera Division", "away_team": "Espanyol", "market": "classic", "competition_cluster": "Spain", "prediction": "1", "status": "pending", "federation": "UEFA", "is_expired": false, "season": "2024 - 2025", "id": 352257, "result": "", "start_date": "2025-04-27T15:15:00", "last_update_at": "2025-04-27T05:41:30.075874", "odds": {"1": 1.442, "X": 4.967, "2": 6.428, "1X": 1.112, "X2": 2.768, "12": 1.162}}, {"home_team": "Sabah Baku", "competition_name": "Premier League", "away_team": "Qarabag Agdam", "market": "classic", "competition_cluster": "Azerbaijan", "prediction": "2", "status": "pending", "federation": "UEFA", "is_expired": false, "season": "2024 - 2025", "id": 352288, "result": "", "start_date": "2025-04-27T17:00:00", "last_update_at": "2025-04-27T05:41:30.075874", "odds": {"1": 5.248, "X": 3.748, "2": 1.52, "1X": 2.274, "X2": 1.108, "12": 1.216}}, {"home_team": "KA Akureyri", "competition_name": "Premier League", "away_team": "FH Hafnarfjordur", "market": "classic", "competition_cluster": "Iceland", "prediction": "12", "status": "pending", "federation": "UEFA", "is_expired": false, "season": "2025", "id": 352330, "result": "", "start_date": "2025-04-27T17:15:00", "last_update_at": "2025-04-27T05:41:30.075874", "odds": {"1": 2.396, "X": 3.402, "2": 2.634, "1X": 1.422, "X2": 1.51, "12": 1.268}}, {"home_team": "Maccabi Netanya", "competition_name": "Championship Group", "away_team": "Hapoel Beer Sheva", "market": "classic", "competition_cluster": "Israel", "prediction": "2", "status": "pending", "federation": "UEFA", "is_expired": false, "season": "2024 - 2025", "id": 352332, "result": "", "start_date": "2025-04-27T18:15:00", "last_update_at": "2025-04-27T05:41:30.075874", "odds": {"1": 6.15, "X": 4.492, "2": 1.42, "1X": 2.72, "X2": 1.104, "12": 1.158}}, {"home_team": "Sanliurfaspor", "competition_name": "TFF First League", "away_team": "Manisa FK", "market": "classic", "competition_cluster": "Turkey", "prediction": "12", "status": "pending", "federation": "UEFA", "is_expired": false, "season": "2024 - 2025", "id": 352442, "result": "", "start_date": "2025-04-27T14:00:00", "last_update_at": "2025-04-27T05:41:30.075874", "odds": {"1": 2.303, "X": 3.317, "2": 2.698, "1X": 1.395, "X2": 1.527, "12": 1.277}}, {"home_team": "Kocaelispor", "competition_name": "TFF First League", "away_team": "Boluspor", "market": "classic", "competition_cluster": "Turkey", "prediction": "1", "status": "pending", "federation": "UEFA", "is_expired": false, "season": "2024 - 2025", "id": 352440, "result": "", "start_date": "2025-04-27T14:00:00", "last_update_at": "2025-04-27T05:41:30.075874", "odds": {"1": 1.677, "X": 3.625, "2": 4.363, "1X": 1.173, "X2": 2.032, "12": 1.242}}, {"home_team": "TS Galaxy", "competition_name": "Premier Soccer League", "away_team": "Sekhukhune United", "market": "classic", "competition_cluster": "South Africa", "prediction": "1X", "status": "pending", "federation": "CAF", "is_expired": false, "season": "2024 - 2025", "id": 352537, "result": "", "start_date": "2025-04-27T14:30:00", "last_update_at": "2025-04-27T05:41:30.075874", "odds": {"1": 1.984, "X": 3.038, "2": 3.868, "1X": 1.22, "X2": 1.737, "12": 1.32}}, {"home_team": "Arsenal Tula", "competition_name": "First League", "away_team": "Rotor Volgograd", "market": "classic", "competition_cluster": "Russia", "prediction": "1X", "status": "pending", "federation": "UEFA", "is_expired": false, "season": "2024 - 2025", "id": 352404, "result": "", "start_date": "2025-04-27T15:00:00", "last_update_at": "2025-04-27T05:41:30.075874", "odds": {"1": 2.145, "X": 2.91, "2": 3.71, "1X": 1.24, "X2": 1.62, "12": 1.37}}, {"home_team": "Boston River", "competition_name": "Primera Division", "away_team": "Miramar Misiones", "market": "classic", "competition_cluster": "Uruguay", "prediction": "12", "status": "pending", "federation": "CONMEBOL", "is_expired": false, "season": "2025 - Apertura", "id": 352554, "result": "", "start_date": "2025-04-27T17:00:00", "last_update_at": "2025-04-27T05:41:30.075874", "odds": {"1": 1.882, "X": 3.202, "2": 4.088, "1X": 1.205, "X2": 1.837, "12": 1.305}}, {"home_team": "Malaga", "competition_name": "Segunda Division", "away_team": "Castellon", "market": "classic", "competition_cluster": "Spain", "prediction": "1X", "status": "pending", "federation": "UEFA", "is_expired": false, "season": "2024 - 2025", "id": 352259, "result": "", "start_date": "2025-04-27T17:30:00", "last_update_at": "2025-04-27T05:41:30.075874", "odds": {"1": 2.773, "X": 3.173, "2": 2.448, "1X": 1.502, "X2": 1.397, "12": 1.322}}, {"home_team": "Almirante Brown", "competition_name": "Primera Nacional", "away_team": "Agropecuario Argentino", "market": "classic", "competition_cluster": "Argentina", "prediction": "1X", "status": "pending", "federation": "CONMEBOL", "is_expired": false, "season": "2025", "id": 352462, "result": "", "start_date": "2025-04-27T19:00:00", "last_update_at": "2025-04-27T05:41:30.075874", "odds": {"1": 2.514, "X": 2.822, "2": 2.91, "1X": 1.313, "X2": 1.457, "12": 1.403}}, {"home_team": "Marseille", "competition_name": "Ligue 1", "away_team": "Brest", "market": "classic", "competition_cluster": "France", "prediction": "1", "status": "pending", "federation": "UEFA", "is_expired": false, "season": "2024 - 2025", "id": 352232, "result": "", "start_date": "2025-04-27T19:45:00", "last_update_at": "2025-04-27T05:41:30.075874", "odds": {"1": 1.487, "X": 4.725, "2": 6.1, "1X": 1.115, "X2": 2.618, "12": 1.175}}, {"home_team": "Orense SC", "competition_name": "Serie A", "away_team": "Independiente del Valle", "market": "classic", "competition_cluster": "Ecuador", "prediction": "2", "status": "pending", "federation": "CONMEBOL", "is_expired": false, "season": "2025 - First Stage", "id": 352511, "result": "", "start_date": "2025-04-27T21:30:00", "last_update_at": "2025-04-27T05:41:30.075874", "odds": {"1": 3.537, "X": 3.297, "2": 1.99, "1X": 1.754, "X2": 1.248, "12": 1.314}}, {"home_team": "US Mondorf-les-Bains", "competition_name": "National Division", "away_team": "Progres Niedercorn", "market": "classic", "competition_cluster": "Luxembourg", "prediction": "2", "status": "pending", "federation": "UEFA", "is_expired": false, "season": "2024 - 2025", "id": 352345, "result": "", "start_date": "2025-04-27T15:00:00", "last_update_at": "2025-04-27T05:41:30.075874", "odds": {"1": 4.305, "X": 3.61, "2": 1.665, "1X": 2.02, "X2": 1.163, "12": 1.217}}, {"home_team": "Leixoes", "competition_name": "Liga Portugal 2", "away_team": "Penafiel", "market": "classic", "competition_cluster": "Portugal", "prediction": "1", "status": "pending", "federation": "UEFA", "is_expired": false, "season": "2024 - 2025", "id": 352394, "result": "", "start_date": "2025-04-27T15:30:00", "last_update_at": "2025-04-27T05:41:30.075874", "odds": {"1": 1.79, "X": 3.387, "2": 4.09, "1X": 1.193, "X2": 1.933, "12": 1.273}}, {"home_team": "Sitra Club", "competition_name": "Premier League", "away_team": "East Riffa", "market": "classic", "competition_cluster": "Bahrain", "prediction": "1X", "status": "pending", "federation": "AFC", "is_expired": false, "season": "2024 - 2025", "id": 352471, "result": "", "start_date": "2025-04-27T17:20:00", "last_update_at": "2025-04-27T05:41:30.075874", "odds": {"1": 2.136, "X": 3.038, "2": 3.128, "1X": 1.298, "X2": 1.592, "12": 1.312}}, {"home_team": "Hercules", "competition_name": "Primera Division RFEF Group 2", "away_team": "Alcorcon", "market": "classic", "competition_cluster": "Spain", "prediction": "1X", "status": "pending", "federation": "UEFA", "is_expired": false, "season": "2024 - 2025", "id": 352271, "result": "", "start_date": "2025-04-27T18:30:00", "last_update_at": "2025-04-27T05:41:30.075874", "odds": {"1": 1.905, "X": 3.207, "2": 3.667, "1X": 1.22, "X2": 1.77, "12": 1.286}}, {"home_team": "Stevenage", "competition_name": "League One", "away_team": "Rotherham", "market": "classic", "competition_cluster": "England", "prediction": "1X", "status": "pending", "federation": "UEFA", "is_expired": false, "season": "2024 - 2025", "id": 352225, "result": "", "start_date": "2025-04-27T14:00:00", "last_update_at": "2025-04-27T05:41:30.075874", "odds": {"1": 2.167, "X": 3.272, "2": 3.3, "1X": 1.295, "X2": 1.645, "12": 1.313}}, {"home_team": "Inter", "competition_name": "Serie A", "away_team": "Roma", "market": "classic", "competition_cluster": "Italy", "prediction": "1", "status": "pending", "federation": "UEFA", "is_expired": false, "season": "2024 - 2025", "id": 352244, "result": "", "start_date": "2025-04-27T14:00:00", "last_update_at": "2025-04-27T05:41:30.075874", "odds": {"1": 1.778, "X": 3.698, "2": 4.607, "1X": 1.187, "X2": 2.013, "12": 1.27}}, {"home_team": "Viking Stavanger", "competition_name": "Eliteserien", "away_team": "Tromso", "market": "classic", "competition_cluster": "Norway", "prediction": "1", "status": "pending", "federation": "UEFA", "is_expired": false, "season": "2025", "id": 352366, "result": "", "start_date": "2025-04-27T18:15:00", "last_update_at": "2025-04-27T05:41:30.075874", "odds": {"1": 1.707, "X": 3.93, "2": 4.443, "1X": 1.193, "X2": 2.073, "12": 1.233}}, {"home_team": "Adanaspor", "competition_name": "TFF First League", "away_team": "Genclerbirligi", "market": "classic", "competition_cluster": "Turkey", "prediction": "2", "status": "pending", "federation": "UEFA", "is_expired": false, "season": "2024 - 2025", "id": 352435, "result": "", "start_date": "2025-04-27T14:00:00", "last_update_at": "2025-04-27T05:41:30.075874", "odds": {"1": 9.583, "X": 5.558, "2": 1.238, "1X": 3.655, "X2": 1.05, "12": 1.122}}, {"home_team": "F91 Dudelange", "competition_name": "National Division", "away_team": "Union Titus Petange", "market": "classic", "competition_cluster": "Luxembourg", "prediction": "1", "status": "pending", "federation": "UEFA", "is_expired": false, "season": "2024 - 2025", "id": 352340, "result": "", "start_date": "2025-04-27T15:00:00", "last_update_at": "2025-04-27T05:41:30.075874", "odds": {"1": 1.43, "X": 4.213, "2": 5.745, "1X": 1.087, "X2": 2.53, "12": 1.17}}, {"home_team": "Liverpool", "competition_name": "Premier League", "away_team": "Tottenham", "market": "classic", "competition_cluster": "England", "prediction": "1", "status": "pending", "federation": "UEFA", "is_expired": false, "season": "2024 - 2025", "id": 352224, "result": "", "start_date": "2025-04-27T16:30:00", "last_update_at": "2025-04-27T05:41:30.075874", "odds": {"1": 1.243, "X": 6.57, "2": 10.367, "1X": 1.047, "X2": 3.913, "12": 1.11}}, {"home_team": "Real Sociedad Tocoa", "competition_name": "Liga Nacional", "away_team": "Victoria La Ceiba", "market": "classic", "competition_cluster": "Honduras", "prediction": "12", "status": "pending", "federation": "CONCACAF", "is_expired": false, "season": "2025 - Clausura", "id": 352591, "result": "", "start_date": "2025-04-27T22:00:00", "last_update_at": "2025-04-27T05:41:30.075874", "odds": {"1": 2.75, "X": 3.0, "2": 2.385, "1X": 1.46, "X2": 1.367, "12": 1.29}}, {"home_team": "Kjelsas", "competition_name": "2. Division", "away_team": "Asker", "market": "classic", "competition_cluster": "Norway", "prediction": "1", "status": "pending", "federation": "UEFA", "is_expired": false, "season": "2025", "id": 352379, "result": "", "start_date": "2025-04-27T13:00:00", "last_update_at": "2025-04-27T05:41:30.075874", "odds": {"1": 1.457, "X": 4.225, "2": 5.193, "1X": 1.11, "X2": 2.42, "12": 1.167}}, {"home_team": "FK Sarajevo", "competition_name": "Premier League", "away_team": "Zeljeznicar Sarajevo", "market": "classic", "competition_cluster": "Bosnia and Herzegovina", "prediction": "1", "status": "pending", "federation": "UEFA", "is_expired": false, "season": "2024 - 2025", "id": 351926, "result": "", "start_date": "2025-04-27T14:00:00", "last_update_at": "2025-04-27T05:41:30.075874", "odds": {"1": 1.673, "X": 3.54, "2": 4.617, "1X": 1.135, "X2": 2.035, "12": 1.235}}, {"home_team": "Moss FK", "competition_name": "1. Division", "away_team": "Stabaek", "market": "classic", "competition_cluster": "Norway", "prediction": "1X", "status": "pending", "federation": "UEFA", "is_expired": false, "season": "2025", "id": 352368, "result": "", "start_date": "2025-04-27T16:00:00", "last_update_at": "2025-04-27T05:41:30.075874", "odds": {"1": 2.537, "X": 3.387, "2": 2.5, "1X": 1.478, "X2": 1.47, "12": 1.277}}, {"home_team": "Gimnastic de Tarragona", "competition_name": "Primera Division RFEF Group 1", "away_team": "Real Union", "market": "classic", "competition_cluster": "Spain", "prediction": "1", "status": "pending", "federation": "UEFA", "is_expired": false, "season": "2024 - 2025", "id": 352265, "result": "", "start_date": "2025-04-27T16:00:00", "last_update_at": "2025-04-27T05:41:30.075874", "odds": {"1": 1.52, "X": 3.73, "2": 5.442, "1X": 1.108, "X2": 2.3, "12": 1.218}}, {"home_team": "Tenerife", "competition_name": "Segunda Division", "away_team": "Eibar", "market": "classic", "competition_cluster": "Spain", "prediction": "1X", "status": "pending", "federation": "UEFA", "is_expired": false, "season": "2024 - 2025", "id": 352260, "result": "", "start_date": "2025-04-27T17:30:00", "last_update_at": "2025-04-27T05:41:30.075874", "odds": {"1": 2.28, "X": 2.95, "2": 3.258, "1X": 1.307, "X2": 1.572, "12": 1.36}}, {"home_team": "Sevilla Atletico", "competition_name": "Primera Division RFEF Group 2", "away_team": "Betis Deportivo Balompie", "market": "classic", "competition_cluster": "Spain", "prediction": "1X", "status": "pending", "federation": "UEFA", "is_expired": false, "season": "2024 - 2025", "id": 352268, "result": "", "start_date": "2025-04-27T11:00:00", "last_update_at": "2025-04-27T05:41:30.075874", "odds": {"1": 2.198, "X": 3.072, "2": 2.993, "1X": 1.318, "X2": 1.564, "12": 1.304}}, {"home_team": "Krylya Sovetov Samara", "competition_name": "Premier League", "away_team": "FC Orenburg", "market": "classic", "competition_cluster": "Russia", "prediction": "1X", "status": "pending", "federation": "UEFA", "is_expired": false, "season": "2024 - 2025", "id": 352397, "result": "", "start_date": "2025-04-27T12:00:00", "last_update_at": "2025-04-27T05:41:30.075874", "odds": {"1": 1.96, "X": 3.82, "2": 3.825, "1X": 1.275, "X2": 1.88, "12": 1.275}}, {"home_team": "Wuhan Three Towns", "competition_name": "Super League", "away_team": "Tianjin Jinmen Tiger", "market": "classic", "competition_cluster": "China", "prediction": "12", "status": "pending", "federation": "AFC", "is_expired": false, "season": "2025", "id": 352498, "result": "", "start_date": "2025-04-27T12:00:00", "last_update_at": "2025-04-27T05:41:30.075874", "odds": {"1": 2.425, "X": 3.372, "2": 2.77, "1X": 1.402, "X2": 1.517, "12": 1.295}}, {"home_team": "Hannover", "competition_name": "2. Bundesliga", "away_team": "FC Koln", "market": "classic", "competition_cluster": "Germany", "prediction": "2", "status": "pending", "federation": "UEFA", "is_expired": false, "season": "2024 - 2025", "id": 352236, "result": "", "start_date": "2025-04-27T12:30:00", "last_update_at": "2025-04-27T05:41:30.075874", "odds": {"1": 3.215, "X": 3.442, "2": 2.14, "1X": 1.665, "X2": 1.327, "12": 1.292}}, {"home_team": "Eidsvold TF", "competition_name": "2. Division", "away_team": "Strindheim", "market": "classic", "competition_cluster": "Norway", "prediction": "1", "status": "pending", "federation": "UEFA", "is_expired": false, "season": "2025", "id": 352378, "result": "", "start_date": "2025-04-27T13:00:00", "last_update_at": "2025-04-27T05:41:30.075874", "odds": {"1": 1.395, "X": 4.975, "2": 4.983, "1X": 1.127, "X2": 2.587, "12": 1.12}}, {"home_team": "Ankaragucu", "competition_name": "TFF First League", "away_team": "Corum", "market": "classic", "competition_cluster": "Turkey", "prediction": "12", "status": "pending", "federation": "UEFA", "is_expired": false, "season": "2024 - 2025", "id": 352436, "result": "", "start_date": "2025-04-27T14:00:00", "last_update_at": "2025-04-27T05:41:30.075874", "odds": {"1": 1.748, "X": 3.69, "2": 3.8, "1X": 1.215, "X2": 1.962, "12": 1.228}}, {"home_team": "Giugliano", "competition_name": "Serie C", "away_team": "Benevento", "market": "classic", "competition_cluster": "Italy", "prediction": "1X", "status": "pending", "federation": "UEFA", "is_expired": false, "season": "2024 - 2025", "id": 352730, "result": "", "start_date": "2025-04-27T19:00:00", "last_update_at": "2025-04-27T05:41:30.075874", "odds": {"1": 2.934, "X": 2.588, "2": 2.578, "1X": 1.406, "X2": 1.312, "12": 1.408}}, {"home_team": "Wil", "competition_name": "Challenge League", "away_team": "Bellinzona", "market": "classic", "competition_cluster": "Switzerland", "prediction": "12", "status": "pending", "federation": "UEFA", "is_expired": false, "season": "2024 - 2025", "id": 352429, "result": "", "start_date": "2025-04-27T13:15:00", "last_update_at": "2025-04-27T05:41:30.075874", "odds": {"1": 2.44, "X": 3.15, "2": 2.624, "1X": 1.404, "X2": 1.478, "12": 1.298}}, {"home_team": "Kauno Zalgiris", "competition_name": "A Lyga", "away_team": "Banga Gargzdai", "market": "classic", "competition_cluster": "Lithuania", "prediction": "1", "status": "pending", "federation": "UEFA", "is_expired": false, "season": "2025", "id": 352337, "result": "", "start_date": "2025-04-27T14:30:00", "last_update_at": "2025-04-27T05:41:30.075874", "odds": {"1": 1.442, "X": 3.878, "2": 6.092, "1X": 1.09, "X2": 2.49, "12": 1.195}}, {"home_team": "Alemannia Aachen", "competition_name": "3. Liga", "away_team": "Osnabruck", "market": "classic", "competition_cluster": "Germany", "prediction": "1X", "status": "pending", "federation": "UEFA", "is_expired": false, "season": "2024 - 2025", "id": 352239, "result": "", "start_date": "2025-04-27T15:30:00", "last_update_at": "2025-04-27T05:41:30.075874", "odds": {"1": 2.232, "X": 3.144, "2": 3.156, "1X": 1.305, "X2": 1.595, "12": 1.335}}, {"home_team": "Zrinjski Mostar", "competition_name": "Premier League", "away_team": "Siroki Brijeg", "market": "classic", "competition_cluster": "Bosnia and Herzegovina", "prediction": "1", "status": "pending", "federation": "UEFA", "is_expired": false, "season": "2024 - 2025", "id": 351928, "result": "", "start_date": "2025-04-27T18:45:00", "last_update_at": "2025-04-27T05:41:30.075874", "odds": {"1": 1.24, "X": 4.825, "2": 11.462, "1X": 1.023, "X2": 3.453, "12": 1.137}}, {"home_team": "SHB Da Nang", "competition_name": "V.League 1", "away_team": "Thanh Hoa FC", "market": "classic", "competition_cluster": "Vietnam", "prediction": "12", "status": "pending", "federation": "AFC", "is_expired": false, "season": "2024 - 2025", "id": 352569, "result": "", "start_date": "2025-04-27T12:00:00", "last_update_at": "2025-04-27T05:41:30.075874", "odds": {"1": 2.78, "X": 3.148, "2": 2.305, "1X": 1.508, "X2": 1.357, "12": 1.278}}, {"home_team": "Ha Noi FC", "competition_name": "V.League 1", "away_team": "Quang Nam", "market": "classic", "competition_cluster": "Vietnam", "prediction": "1", "status": "pending", "federation": "AFC", "is_expired": false, "season": "2024 - 2025", "id": 352570, "result": "", "start_date": "2025-04-27T13:15:00", "last_update_at": "2025-04-27T05:41:30.075874", "odds": {"1": 1.27, "X": 4.912, "2": 8.238, "1X": 1.04, "X2": 3.295, "12": 1.125}}, {"home_team": "Levanger FK", "competition_name": "2. Division", "away_team": "Grorud", "market": "classic", "competition_cluster": "Norway", "prediction": "12", "status": "pending", "federation": "UEFA", "is_expired": false, "season": "2025", "id": 352381, "result": "", "start_date": "2025-04-27T14:30:00", "last_update_at": "2025-04-27T05:41:30.075874", "odds": {"1": 1.917, "X": 3.688, "2": 3.185, "1X": 1.287, "X2": 1.75, "12": 1.213}}, {"home_team": "MSK Zilina", "competition_name": "Championship Group", "away_team": "Spartak Trnava", "market": "classic", "competition_cluster": "Slovakia", "prediction": "12", "status": "pending", "federation": "UEFA", "is_expired": false, "season": "2024 - 2025", "id": 352412, "result": "", "start_date": "2025-04-27T17:00:00", "last_update_at": "2025-04-27T05:41:30.075874", "odds": {"1": 2.21, "X": 3.362, "2": 2.905, "1X": 1.355, "X2": 1.587, "12": 1.27}}, {"home_team": "Palestino Santiago", "competition_name": "Primera Division", "away_team": "Universidad de Chile", "market": "classic", "competition_cluster": "Chile", "prediction": "2", "status": "pending", "federation": "CONMEBOL", "is_expired": false, "season": "2025", "id": 352497, "result": "", "start_date": "2025-04-27T20:00:00", "last_update_at": "2025-04-27T05:41:30.075874", "odds": {"1": 3.887, "X": 3.552, "2": 1.863, "1X": 1.862, "X2": 1.227, "12": 1.267}}, {"home_team": "Ituano SP", "competition_name": "Serie C", "away_team": "Tombense MG", "market": "classic", "competition_cluster": "Brazil", "prediction": "1X", "status": "pending", "federation": "CONMEBOL", "is_expired": false, "season": "2025", "id": 352481, "result": "", "start_date": "2025-04-27T20:30:00", "last_update_at": "2025-04-27T05:41:30.075874", "odds": {"1": 2.0, "X": 2.96, "2": 3.662, "1X": 1.222, "X2": 1.684, "12": 1.32}}, {"home_team": "Odra Opole", "competition_name": "First League", "away_team": "Gornik Leczna", "market": "classic", "competition_cluster": "Poland", "prediction": "12", "status": "pending", "federation": "UEFA", "is_expired": false, "season": "2024 - 2025", "id": 352385, "result": "", "start_date": "2025-04-27T11:00:00", "last_update_at": "2025-04-27T05:41:30.075874", "odds": {"1": 2.613, "X": 3.097, "2": 2.56, "1X": 1.45, "X2": 1.414, "12": 1.318}}, {"home_team": "Assyriska Foreningen", "competition_name": "Division 1", "away_team": "Hammarby Talang FF", "market": "classic", "competition_cluster": "Sweden", "prediction": "2", "status": "pending", "federation": "UEFA", "is_expired": false, "season": "2025", "id": 352424, "result": "", "start_date": "2025-04-27T15:00:00", "last_update_at": "2025-04-27T05:41:30.075874", "odds": {"1": 3.157, "X": 3.55, "2": 1.973, "1X": 1.7, "X2": 1.285, "12": 1.235}}, {"home_team": "Perugia", "competition_name": "Serie C", "away_team": "Pontedera", "market": "classic", "competition_cluster": "Italy", "prediction": "1X", "status": "pending", "federation": "UEFA", "is_expired": false, "season": "2024 - 2025", "id": 352252, "result": "", "start_date": "2025-04-27T15:30:00", "last_update_at": "2025-04-27T05:41:30.075874", "odds": {"1": 2.496, "X": 3.148, "2": 2.516, "1X": 1.418, "X2": 1.436, "12": 1.304}}, {"home_team": "Almere City FC", "competition_name": "Eredivisie", "away_team": "Go Ahead Eagles", "market": "classic", "competition_cluster": "Netherlands", "prediction": "12", "status": "pending", "federation": "UEFA", "is_expired": false, "season": "2024 - 2025", "id": 352352, "result": "", "start_date": "2025-04-27T15:45:00", "last_update_at": "2025-04-27T05:41:30.075874", "odds": {"1": 2.512, "X": 3.748, "2": 2.552, "1X": 1.487, "X2": 1.493, "12": 1.265}}, {"home_team": "Deportivo Guastatoya", "competition_name": "Liga Nacional", "away_team": "Deportivo Mixco", "market": "classic", "competition_cluster": "Guatemala", "prediction": "1X", "status": "pending", "federation": "CONCACAF", "is_expired": false, "season": "2025 - Clausura", "id": 352589, "result": "", "start_date": "2025-04-27T22:00:00", "last_update_at": "2025-04-27T05:41:30.075874", "odds": {"1": 1.855, "X": 3.135, "2": 4.02, "1X": 1.187, "X2": 1.813, "12": 1.283}}, {"home_team": "BG Pathum United", "competition_name": "Thai League 1", "away_team": "Sukhothai FC", "market": "classic", "competition_cluster": "Thailand", "prediction": "1", "status": "pending", "federation": "AFC", "is_expired": false, "season": "2024 - 2025", "id": 352544, "result": "", "start_date": "2025-04-27T12:00:00", "last_update_at": "2025-04-27T05:41:30.075874", "odds": {"1": 1.372, "X": 4.69, "2": 5.84, "1X": 1.092, "X2": 2.735, "12": 1.145}}, {"home_team": "Tarazona", "competition_name": "Primera Division RFEF Group 1", "away_team": "Ponferradina", "market": "classic", "competition_cluster": "Spain", "prediction": "1X", "status": "pending", "federation": "UEFA", "is_expired": false, "season": "2024 - 2025", "id": 352264, "result": "", "start_date": "2025-04-27T14:30:00", "last_update_at": "2025-04-27T05:41:30.075874", "odds": {"1": 3.103, "X": 2.67, "2": 2.41, "1X": 1.472, "X2": 1.302, "12": 1.4}}, {"home_team": "Perez Zeledon", "competition_name": "Primera Division", "away_team": "Municipal Liberia", "market": "classic", "competition_cluster": "Costa Rica", "prediction": "1X", "status": "pending", "federation": "CONCACAF", "is_expired": false, "season": "2025 - Clausura", "id": 352585, "result": "", "start_date": "2025-04-27T22:00:00", "last_update_at": "2025-04-27T05:41:30.075874", "odds": {"1": 2.347, "X": 3.105, "2": 2.898, "1X": 1.343, "X2": 1.525, "12": 1.324}}, {"home_team": "SPAL", "competition_name": "Serie C", "away_team": "Gubbio", "market": "classic", "competition_cluster": "Italy", "prediction": "12", "status": "pending", "federation": "UEFA", "is_expired": false, "season": "2024 - 2025", "id": 352256, "result": "", "start_date": "2025-04-27T15:30:00", "last_update_at": "2025-04-27T05:41:30.075874", "odds": {"1": 1.932, "X": 3.398, "2": 3.352, "1X": 1.268, "X2": 1.714, "12": 1.258}}, {"home_team": "Varnsdorf", "competition_name": "National League", "away_team": "SK Prostejov", "market": "classic", "competition_cluster": "Czech Republic", "prediction": "12", "status": "pending", "federation": "UEFA", "is_expired": false, "season": "2024 - 2025", "id": 352303, "result": "", "start_date": "2025-04-27T16:00:00", "last_update_at": "2025-04-27T05:41:30.075874", "odds": {"1": 1.892, "X": 3.348, "2": 3.518, "1X": 1.242, "X2": 1.763, "12": 1.26}}, {"home_team": "Penarol Montevideo", "competition_name": "Primera Division", "away_team": "Cerro Montevideo", "market": "classic", "competition_cluster": "Uruguay", "prediction": "1", "status": "pending", "federation": "CONMEBOL", "is_expired": false, "season": "2025 - Apertura", "id": 352596, "result": "", "start_date": "2025-04-27T22:15:00", "last_update_at": "2025-04-27T05:41:30.075874", "odds": {"1": 1.432, "X": 3.915, "2": 7.633, "1X": 1.072, "X2": 2.595, "12": 1.222}}, {"home_team": "Ruch Chorzow", "competition_name": "First League", "away_team": "Stal Rzeszow", "market": "classic", "competition_cluster": "Poland", "prediction": "12", "status": "pending", "federation": "UEFA", "is_expired": false, "season": "2024 - 2025", "id": 352386, "result": "", "start_date": "2025-04-27T13:30:00", "last_update_at": "2025-04-27T05:41:30.075874", "odds": {"1": 1.827, "X": 3.663, "2": 3.617, "1X": 1.236, "X2": 1.862, "12": 1.238}}, {"home_team": "Catanzaro", "competition_name": "Serie B", "away_team": "Palermo", "market": "classic", "competition_cluster": "Italy", "prediction": "1X", "status": "pending", "federation": "UEFA", "is_expired": false, "season": "2024 - 2025", "id": 352726, "result": "", "start_date": "2025-04-27T14:00:00", "last_update_at": "2025-04-27T05:41:30.075874", "odds": {"1": 2.697, "X": 3.233, "2": 2.53, "1X": 1.49, "X2": 1.428, "12": 1.325}}, {"home_team": "Racing Santander", "competition_name": "Segunda Division", "away_team": "Deportivo La Coruna", "market": "classic", "competition_cluster": "Spain", "prediction": "1X", "status": "pending", "federation": "UEFA", "is_expired": false, "season": "2024 - 2025", "id": 352258, "result": "", "start_date": "2025-04-27T15:15:00", "last_update_at": "2025-04-27T05:41:30.075874", "odds": {"1": 1.845, "X": 3.662, "2": 3.687, "1X": 1.247, "X2": 1.878, "12": 1.25}}, {"home_team": "Atalanta", "competition_name": "Serie A", "away_team": "Lecce", "market": "classic", "competition_cluster": "Italy", "prediction": "1", "status": "pending", "federation": "UEFA", "is_expired": false, "season": "2024 - 2025", "id": 352716, "result": "", "start_date": "2025-04-27T19:45:00", "last_update_at": "2025-04-27T05:41:30.075874", "odds": {"1": 1.233, "X": 6.412, "2": 12.583, "1X": 1.03, "X2": 4.134, "12": 1.11}}, {"home_team": "Khonkaen United", "competition_name": "Thai League 1", "away_team": "Chiangrai United FC", "market": "classic", "competition_cluster": "Thailand", "prediction": "1X", "status": "pending", "federation": "AFC", "is_expired": false, "season": "2024 - 2025", "id": 352545, "result": "", "start_date": "2025-04-27T12:00:00", "last_update_at": "2025-04-27T05:41:30.075874", "odds": {"1": 2.678, "X": 3.43, "2": 2.208, "1X": 1.55, "X2": 1.403, "12": 1.245}}, {"home_team": "Bochum", "competition_name": "Bundesliga", "away_team": "Union Berlin", "market": "classic", "competition_cluster": "Germany", "prediction": "12", "status": "pending", "federation": "UEFA", "is_expired": false, "season": "2024 - 2025", "id": 352233, "result": "", "start_date": "2025-04-27T14:30:00", "last_update_at": "2025-04-27T05:41:30.075874", "odds": {"1": 2.302, "X": 3.502, "2": 3.023, "1X": 1.372, "X2": 1.592, "12": 1.29}}, {"home_team": "Etar Veliko Tarnovo", "competition_name": "Second PFL", "away_team": "Fratria Varna", "market": "classic", "competition_cluster": "Bulgaria", "prediction": "1", "status": "pending", "federation": "UEFA", "is_expired": false, "season": "2024 - 2025", "id": 352296, "result": "", "start_date": "2025-04-27T15:00:00", "last_update_at": "2025-04-27T05:41:30.075874", "odds": {"1": 1.8, "X": 3.193, "2": 4.183, "1X": 1.155, "X2": 1.83, "12": 1.25}}, {"home_team": "Fola Esch", "competition_name": "National Division", "away_team": "Swift Hesperange", "market": "classic", "competition_cluster": "Luxembourg", "prediction": "2", "status": "pending", "federation": "UEFA", "is_expired": false, "season": "2024 - 2025", "id": 352341, "result": "", "start_date": "2025-04-27T15:00:00", "last_update_at": "2025-04-27T05:41:30.075874", "odds": {"1": 9.738, "X": 6.1, "2": 1.185, "1X": 3.93, "X2": 1.027, "12": 1.073}}, {"home_team": "Rodange 91", "competition_name": "National Division", "away_team": "Victoria Rosport", "market": "classic", "competition_cluster": "Luxembourg", "prediction": "12", "status": "pending", "federation": "UEFA", "is_expired": false, "season": "2024 - 2025", "id": 352343, "result": "", "start_date": "2025-04-27T15:00:00", "last_update_at": "2025-04-27T05:41:30.075874", "odds": {"1": 2.38, "X": 3.483, "2": 2.435, "1X": 1.46, "X2": 1.463, "12": 1.24}}, {"home_team": "Rubin Kazan", "competition_name": "Premier League", "away_team": "Fakel Voronezh", "market": "classic", "competition_cluster": "Russia", "prediction": "1X", "status": "pending", "federation": "UEFA", "is_expired": false, "season": "2024 - 2025", "id": 352399, "result": "", "start_date": "2025-04-27T17:00:00", "last_update_at": "2025-04-27T05:41:30.075874", "odds": {"1": 2.105, "X": 3.26, "2": 3.975, "1X": 1.26, "X2": 1.755, "12": 1.355}}, {"home_team": "Progreso Montevideo", "competition_name": "Primera Division", "away_team": "Liverpool Montevideo", "market": "classic", "competition_cluster": "Uruguay", "prediction": "2", "status": "pending", "federation": "CONMEBOL", "is_expired": false, "season": "2025 - Apertura", "id": 352555, "result": "", "start_date": "2025-04-27T19:15:00", "last_update_at": "2025-04-27T05:41:30.075874", "odds": {"1": 3.67, "X": 3.5, "2": 1.89, "1X": 1.833, "X2": 1.242, "12": 1.267}}, {"home_team": "Rosenborg", "competition_name": "Eliteserien", "away_team": "Molde", "market": "classic", "competition_cluster": "Norway", "prediction": "1", "status": "pending", "federation": "UEFA", "is_expired": false, "season": "2025", "id": 352359, "result": "", "start_date": "2025-04-27T13:30:00", "last_update_at": "2025-04-27T05:41:30.075874", "odds": {"1": 1.707, "X": 4.022, "2": 4.298, "1X": 1.202, "X2": 2.075, "12": 1.22}}, {"home_team": "Vllaznia Shkoder", "competition_name": "Superliga", "away_team": "Laci", "market": "classic", "competition_cluster": "Albania", "prediction": "12", "status": "pending", "federation": "UEFA", "is_expired": false, "season": "2024 - 2025", "id": 352276, "result": "", "start_date": "2025-04-27T14:30:00", "last_update_at": "2025-04-27T05:41:30.075874", "odds": {"1": 1.803, "X": 3.213, "2": 4.143, "1X": 1.155, "X2": 1.775, "12": 1.265}}, {"home_team": "Vestri", "competition_name": "Premier League", "away_team": "Breidablik Kopavogur", "market": "classic", "competition_cluster": "Iceland", "prediction": "2", "status": "pending", "federation": "UEFA", "is_expired": false, "season": "2025", "id": 352329, "result": "", "start_date": "2025-04-27T15:00:00", "last_update_at": "2025-04-27T05:41:30.075874", "odds": {"1": 5.24, "X": 4.26, "2": 1.494, "1X": 2.424, "X2": 1.118, "12": 1.182}}, {"home_team": "Ludogorets Razgrad", "competition_name": "Championship Group", "away_team": "Cherno more Varna", "market": "classic", "competition_cluster": "Bulgaria", "prediction": "1", "status": "pending", "federation": "UEFA", "is_expired": false, "season": "2024 - 2025", "id": 352297, "result": "", "start_date": "2025-04-27T18:30:00", "last_update_at": "2025-04-27T05:41:30.075874", "odds": {"1": 1.395, "X": 4.075, "2": 8.042, "1X": 1.063, "X2": 2.777, "12": 1.203}}, {"home_team": "Atletico Mitre", "competition_name": "Primera Nacional", "away_team": "Chacarita Juniors", "market": "classic", "competition_cluster": "Argentina", "prediction": "1X", "status": "pending", "federation": "CONMEBOL", "is_expired": false, "season": "2025", "id": 352466, "result": "", "start_date": "2025-04-27T21:00:00", "last_update_at": "2025-04-27T05:41:30.075874", "odds": {"1": 2.463, "X": 2.643, "2": 3.353, "1X": 1.294, "X2": 1.484, "12": 1.426}}, {"home_team": "Montpellier", "competition_name": "Ligue 1", "away_team": "Reims", "market": "classic", "competition_cluster": "France", "prediction": "2", "status": "pending", "federation": "UEFA", "is_expired": false, "season": "2024 - 2025", "id": 352230, "result": "", "start_date": "2025-04-27T16:15:00", "last_update_at": "2025-04-27T05:41:30.075874", "odds": {"1": 4.523, "X": 3.87, "2": 1.757, "1X": 2.045, "X2": 1.188, "12": 1.257}}, {"home_team": "Temperley", "competition_name": "Primera Nacional", "away_team": "Estudiantes Rio Cuarto", "market": "classic", "competition_cluster": "Argentina", "prediction": "1X", "status": "pending", "federation": "CONMEBOL", "is_expired": false, "season": "2025", "id": 352463, "result": "", "start_date": "2025-04-27T19:30:00", "last_update_at": "2025-04-27T05:41:30.075874", "odds": {"1": 2.558, "X": 2.695, "2": 3.087, "1X": 1.338, "X2": 1.462, "12": 1.408}}, {"home_team": "Heerenveen", "competition_name": "Eredivisie", "away_team": "NEC Nijmegen", "market": "classic", "competition_cluster": "Netherlands", "prediction": "12", "status": "pending", "federation": "UEFA", "is_expired": false, "season": "2024 - 2025", "id": 352351, "result": "", "start_date": "2025-04-27T13:30:00", "last_update_at": "2025-04-27T05:41:30.075874", "odds": {"1": 1.997, "X": 3.63, "2": 3.58, "1X": 1.273, "X2": 1.78, "12": 1.277}}, {"home_team": "Pakhtakor Tashkent", "competition_name": "Super League", "away_team": "Shurtan Guzar", "market": "classic", "competition_cluster": "Uzbekistan", "prediction": "1", "status": "pending", "federation": "AFC", "is_expired": false, "season": "2025", "id": 352565, "result": "", "start_date": "2025-04-27T14:00:00", "last_update_at": "2025-04-27T05:41:30.075874", "odds": {"1": 1.175, "X": 5.74, "2": 13.75, "1X": 1.015, "X2": 4.365, "12": 1.105}}, {"home_team": "Torslanda IK", "competition_name": "Division 1", "away_team": "Angelholms", "market": "classic", "competition_cluster": "Sweden", "prediction": "1X", "status": "pending", "federation": "UEFA", "is_expired": false, "season": "2025", "id": 352427, "result": "", "start_date": "2025-04-27T15:00:00", "last_update_at": "2025-04-27T05:41:30.075874", "odds": {"1": 1.98, "X": 3.354, "2": 3.28, "1X": 1.293, "X2": 1.71, "12": 1.27}}, {"home_team": "Moreirense", "competition_name": "Primeira Liga", "away_team": "Nacional", "market": "classic", "competition_cluster": "Portugal", "prediction": "1X", "status": "pending", "federation": "UEFA", "is_expired": false, "season": "2024 - 2025", "id": 352388, "result": "", "start_date": "2025-04-27T15:30:00", "last_update_at": "2025-04-27T05:41:30.075874", "odds": {"1": 2.16, "X": 3.063, "2": 3.657, "1X": 1.26, "X2": 1.662, "12": 1.355}}, {"home_team": "Konyaspor", "competition_name": "Super Lig", "away_team": "Adana Demirspor", "market": "classic", "competition_cluster": "Turkey", "prediction": "1", "status": "pending", "federation": "UEFA", "is_expired": false, "season": "2024 - 2025", "id": 352431, "result": "", "start_date": "2025-04-27T14:00:00", "last_update_at": "2025-04-27T05:41:30.075874", "odds": {"1": 1.163, "X": 7.542, "2": 13.667, "1X": 1.03, "X2": 4.77, "12": 1.084}}, {"home_team": "Merida AD", "competition_name": "Primera Division RFEF Group 2", "away_team": "Antequera", "market": "classic", "competition_cluster": "Spain", "prediction": "12", "status": "pending", "federation": "UEFA", "is_expired": false, "season": "2024 - 2025", "id": 352269, "result": "", "start_date": "2025-04-27T14:30:00", "last_update_at": "2025-04-27T05:41:30.075874", "odds": {"1": 2.237, "X": 2.998, "2": 2.985, "1X": 1.32, "X2": 1.558, "12": 1.306}}, {"home_team": "Potenza", "competition_name": "Serie C", "away_team": "Catania", "market": "classic", "competition_cluster": "Italy", "prediction": "12", "status": "pending", "federation": "UEFA", "is_expired": false, "season": "2024 - 2025", "id": 352733, "result": "", "start_date": "2025-04-27T19:00:00", "last_update_at": "2025-04-27T05:41:30.075874", "odds": {"1": 2.336, "X": 3.09, "2": 2.762, "1X": 1.37, "X2": 1.482, "12": 1.288}}, {"home_team": "Kairat Almaty", "competition_name": "Premier League", "away_team": "Tobol Kostanay", "market": "classic", "competition_cluster": "Kazakhstan", "prediction": "1", "status": "pending", "federation": "UEFA", "is_expired": false, "season": "2025", "id": 352334, "result": "", "start_date": "2025-04-27T13:00:00", "last_update_at": "2025-04-27T05:41:30.075874", "odds": {"1": 1.59, "X": 3.642, "2": 5.008, "1X": 1.125, "X2": 2.165, "12": 1.22}}, {"home_team": "Racing de Cordoba", "competition_name": "Primera Nacional", "away_team": "Ferro Carril Oeste", "market": "classic", "competition_cluster": "Argentina", "prediction": "1X", "status": "pending", "federation": "CONMEBOL", "is_expired": false, "season": "2025", "id": 352465, "result": "", "start_date": "2025-04-27T20:00:00", "last_update_at": "2025-04-27T05:41:30.075874", "odds": {"1": 2.145, "X": 2.948, "2": 3.487, "1X": 1.28, "X2": 1.642, "12": 1.336}}, {"home_team": "Mjallby", "competition_name": "Allsvenskan", "away_team": "Degerfors", "market": "classic", "competition_cluster": "Sweden", "prediction": "1", "status": "pending", "federation": "UEFA", "is_expired": false, "season": "2025", "id": 352417, "result": "", "start_date": "2025-04-27T13:00:00", "last_update_at": "2025-04-27T05:41:30.075874", "odds": {"1": 1.54, "X": 4.192, "2": 5.592, "1X": 1.13, "X2": 2.397, "12": 1.212}}, {"home_team": "Navbahor Namangan", "competition_name": "Super League", "away_team": "Buxoro FK", "market": "classic", "competition_cluster": "Uzbekistan", "prediction": "1", "status": "pending", "federation": "AFC", "is_expired": false, "season": "2025", "id": 352564, "result": "", "start_date": "2025-04-27T14:00:00", "last_update_at": "2025-04-27T05:41:30.075874", "odds": {"1": 1.62, "X": 3.42, "2": 5.062, "1X": 1.13, "X2": 2.11, "12": 1.253}}, {"home_team": "Gimnasia Mendoza", "competition_name": "Primera Nacional", "away_team": "Nueva Chicago", "market": "classic", "competition_cluster": "Argentina", "prediction": "1", "status": "pending", "federation": "CONMEBOL", "is_expired": false, "season": "2025", "id": 352464, "result": "", "start_date": "2025-04-27T20:00:00", "last_update_at": "2025-04-27T05:41:30.075874", "odds": {"1": 1.537, "X": 3.573, "2": 6.44, "1X": 1.082, "X2": 2.34, "12": 1.26}}, {"home_team": "Coban Imperial", "competition_name": "Liga Nacional", "away_team": "Municipal", "market": "classic", "competition_cluster": "Guatemala", "prediction": "1X", "status": "pending", "federation": "CONCACAF", "is_expired": false, "season": "2025 - Clausura", "id": 352587, "result": "", "start_date": "2025-04-27T22:00:00", "last_update_at": "2025-04-27T05:41:30.075874", "odds": {"1": 2.527, "X": 2.445, "2": 3.257, "1X": 1.27, "X2": 1.437, "12": 1.447}}, {"home_team": "Nantes", "competition_name": "Ligue 1", "away_team": "Toulouse", "market": "classic", "competition_cluster": "France", "prediction": "12", "status": "pending", "federation": "UEFA", "is_expired": false, "season": "2024 - 2025", "id": 352231, "result": "", "start_date": "2025-04-27T16:15:00", "last_update_at": "2025-04-27T05:41:30.075874", "odds": {"1": 2.92, "X": 3.362, "2": 2.438, "1X": 1.52, "X2": 1.395, "12": 1.318}}, {"home_team": "Venezia", "competition_name": "Serie A", "away_team": "Milan", "market": "classic", "competition_cluster": "Italy", "prediction": "2", "status": "pending", "federation": "UEFA", "is_expired": false, "season": "2024 - 2025", "id": 352242, "result": "", "start_date": "2025-04-27T11:30:00", "last_update_at": "2025-04-27T05:41:30.075874", "odds": {"1": 4.798, "X": 4.003, "2": 1.698, "1X": 2.147, "X2": 1.173, "12": 1.237}}, {"home_team": "Hamburger", "competition_name": "2. Bundesliga", "away_team": "Karlsruher", "market": "classic", "competition_cluster": "Germany", "prediction": "1", "status": "pending", "federation": "UEFA", "is_expired": false, "season": "2024 - 2025", "id": 352235, "result": "", "start_date": "2025-04-27T12:30:00", "last_update_at": "2025-04-27T05:41:30.075874", "odds": {"1": 1.482, "X": 4.817, "2": 5.417, "1X": 1.14, "X2": 2.548, "12": 1.168}}, {"home_team": "FSC Mariupol", "competition_name": "First League", "away_team": "FC Minaj", "market": "classic", "competition_cluster": "Ukraine", "prediction": "12", "status": "pending", "federation": "UEFA", "is_expired": false, "season": "2025 - Second Stage", "id": 352450, "result": "", "start_date": "2025-04-27T12:30:00", "last_update_at": "2025-04-27T05:41:30.075874", "odds": {"1": 2.245, "X": 3.12, "2": 2.918, "1X": 1.352, "X2": 1.525, "12": 1.293}}, {"home_team": "Fatih Karagumruk", "competition_name": "TFF First League", "away_team": "Keciorengucu", "market": "classic", "competition_cluster": "Turkey", "prediction": "1", "status": "pending", "federation": "UEFA", "is_expired": false, "season": "2024 - 2025", "id": 352438, "result": "", "start_date": "2025-04-27T14:00:00", "last_update_at": "2025-04-27T05:41:30.075874", "odds": {"1": 1.673, "X": 3.688, "2": 4.227, "1X": 1.178, "X2": 2.062, "12": 1.228}}, {"home_team": "Pescara", "competition_name": "Serie C", "away_team": "Campobasso", "market": "classic", "competition_cluster": "Italy", "prediction": "12", "status": "pending", "federation": "UEFA", "is_expired": false, "season": "2024 - 2025", "id": 352253, "result": "", "start_date": "2025-04-27T15:30:00", "last_update_at": "2025-04-27T05:41:30.075874", "odds": {"1": 1.976, "X": 2.888, "2": 3.846, "1X": 1.188, "X2": 1.712, "12": 1.35}}, {"home_team": "Trabzonspor", "competition_name": "Super Lig", "away_team": "Alanyaspor", "market": "classic", "competition_cluster": "Turkey", "prediction": "1", "status": "pending", "federation": "UEFA", "is_expired": false, "season": "2024 - 2025", "id": 352432, "result": "", "start_date": "2025-04-27T14:00:00", "last_update_at": "2025-04-27T05:41:30.075874", "odds": {"1": 1.748, "X": 3.672, "2": 4.527, "1X": 1.19, "X2": 2.03, "12": 1.27}}, {"home_team": "Real Zaragoza", "competition_name": "Segunda Division", "away_team": "Huesca", "market": "classic", "competition_cluster": "Spain", "prediction": "1", "status": "pending", "federation": "UEFA", "is_expired": false, "season": "2024 - 2025", "id": 352261, "result": "", "start_date": "2025-04-27T20:00:00", "last_update_at": "2025-04-27T05:41:30.075874", "odds": {"1": 1.83, "X": 3.198, "2": 4.378, "1X": 1.187, "X2": 1.878, "12": 1.322}}, {"home_team": "Paysandu PA", "competition_name": "Serie B", "away_team": "CRB AL", "market": "classic", "competition_cluster": "Brazil", "prediction": "12", "status": "pending", "federation": "CONMEBOL", "is_expired": false, "season": "2025", "id": 352193, "result": "", "start_date": "2025-04-27T21:00:00", "last_update_at": "2025-04-27T05:41:30.075874", "odds": {"1": 2.02, "X": 3.115, "2": 3.788, "1X": 1.242, "X2": 1.727, "12": 1.338}}, {"home_team": "Marquense", "competition_name": "Liga Nacional", "away_team": "Deportivo Malacateco", "market": "classic", "competition_cluster": "Guatemala", "prediction": "12", "status": "pending", "federation": "CONCACAF", "is_expired": false, "season": "2025 - Clausura", "id": 352590, "result": "", "start_date": "2025-04-27T22:00:00", "last_update_at": "2025-04-27T05:41:30.075874", "odds": {"1": 1.985, "X": 3.07, "2": 3.49, "1X": 1.24, "X2": 1.683, "12": 1.293}}, {"home_team": "Kaiserslautern", "competition_name": "2. Bundesliga", "away_team": "Schalke 04", "market": "classic", "competition_cluster": "Germany", "prediction": "12", "status": "pending", "federation": "UEFA", "is_expired": false, "season": "2024 - 2025", "id": 352237, "result": "", "start_date": "2025-04-27T12:30:00", "last_update_at": "2025-04-27T05:41:30.075874", "odds": {"1": 2.058, "X": 3.628, "2": 3.255, "1X": 1.312, "X2": 1.717, "12": 1.267}}, {"home_team": "UNA Strassen", "competition_name": "National Division", "away_team": "FC Mondercange", "market": "classic", "competition_cluster": "Luxembourg", "prediction": "1", "status": "pending", "federation": "UEFA", "is_expired": false, "season": "2024 - 2025", "id": 352344, "result": "", "start_date": "2025-04-27T15:00:00", "last_update_at": "2025-04-27T05:41:30.075874", "odds": {"1": 1.117, "X": 7.0, "2": 16.375, "1X": 1.015, "X2": 4.825, "12": 1.06}}, {"home_team": "Trelleborgs", "competition_name": "Superettan", "away_team": "Varbergs BoIS", "market": "classic", "competition_cluster": "Sweden", "prediction": "1X", "status": "pending", "federation": "UEFA", "is_expired": false, "season": "2025", "id": 352422, "result": "", "start_date": "2025-04-27T12:00:00", "last_update_at": "2025-04-27T05:41:30.075874", "odds": {"1": 2.142, "X": 3.317, "2": 3.133, "1X": 1.333, "X2": 1.647, "12": 1.297}}, {"home_team": "Sakaryaspor", "competition_name": "TFF First League", "away_team": "Erzurumspor", "market": "classic", "competition_cluster": "Turkey", "prediction": "1X", "status": "pending", "federation": "UEFA", "is_expired": false, "season": "2024 - 2025", "id": 352441, "result": "", "start_date": "2025-04-27T14:00:00", "last_update_at": "2025-04-27T05:41:30.075874", "odds": {"1": 2.88, "X": 3.178, "2": 2.262, "1X": 1.56, "X2": 1.35, "12": 1.308}}, {"home_team": "AIK Stockholm", "competition_name": "Allsvenskan", "away_team": "Elfsborg", "market": "classic", "competition_cluster": "Sweden", "prediction": "1X", "status": "pending", "federation": "UEFA", "is_expired": false, "season": "2025", "id": 352418, "result": "", "start_date": "2025-04-27T15:00:00", "last_update_at": "2025-04-27T05:41:30.075874", "odds": {"1": 2.327, "X": 3.342, "2": 2.978, "1X": 1.37, "X2": 1.57, "12": 1.307}}, {"home_team": "Juventus", "competition_name": "Serie A", "away_team": "Monza", "market": "classic", "competition_cluster": "Italy", "prediction": "1", "status": "pending", "federation": "UEFA", "is_expired": false, "season": "2024 - 2025", "id": 352245, "result": "", "start_date": "2025-04-27T17:00:00", "last_update_at": "2025-04-27T05:41:30.075874", "odds": {"1": 1.18, "X": 7.175, "2": 15.917, "1X": 1.022, "X2": 4.7, "12": 1.09}}, {"home_team": "Angers", "competition_name": "Ligue 1", "away_team": "Lille", "market": "classic", "competition_cluster": "France", "prediction": "2", "status": "pending", "federation": "UEFA", "is_expired": false, "season": "2024 - 2025", "id": 352228, "result": "", "start_date": "2025-04-27T14:00:00", "last_update_at": "2025-04-27T05:41:30.075874", "odds": {"1": 6.525, "X": 4.088, "2": 1.543, "1X": 2.438, "X2": 1.107, "12": 1.222}}, {"home_team": "Partizani Tirana", "competition_name": "Superliga", "away_team": "Elbasani", "market": "classic", "competition_cluster": "Albania", "prediction": "12", "status": "pending", "federation": "UEFA", "is_expired": false, "season": "2024 - 2025", "id": 352277, "result": "", "start_date": "2025-04-27T16:00:00", "last_update_at": "2025-04-27T05:41:30.075874", "odds": {"1": 1.83, "X": 3.063, "2": 4.243, "1X": 1.155, "X2": 1.81, "12": 1.275}}, {"home_team": "Muangthong United", "competition_name": "Thai League 1", "away_team": "Nakhon Ratchasima FC", "market": "classic", "competition_cluster": "Thailand", "prediction": "1", "status": "pending", "federation": "AFC", "is_expired": false, "season": "2024 - 2025", "id": 352546, "result": "", "start_date": "2025-04-27T12:00:00", "last_update_at": "2025-04-27T05:41:30.075874", "odds": {"1": 1.362, "X": 4.6, "2": 5.952, "1X": 1.09, "X2": 2.723, "12": 1.145}}, {"home_team": "Korona Kielce", "competition_name": "Ekstraklasa", "away_team": "Jagiellonia Bialystok", "market": "classic", "competition_cluster": "Poland", "prediction": "2", "status": "pending", "federation": "UEFA", "is_expired": false, "season": "2024 - 2025", "id": 352382, "result": "", "start_date": "2025-04-27T11:15:00", "last_update_at": "2025-04-27T05:41:30.075874", "odds": {"1": 3.105, "X": 3.408, "2": 2.182, "1X": 1.64, "X2": 1.337, "12": 1.298}}, {"home_team": "Arendal", "competition_name": "2. Division", "away_team": "Traeff", "market": "classic", "competition_cluster": "Norway", "prediction": "1", "status": "pending", "federation": "UEFA", "is_expired": false, "season": "2025", "id": 352369, "result": "", "start_date": "2025-04-27T12:00:00", "last_update_at": "2025-04-27T05:41:30.075874", "odds": {"1": 1.628, "X": 4.02, "2": 4.062, "1X": 1.19, "X2": 2.053, "12": 1.188}}, {"home_team": "PAOK Thessaloniki", "competition_name": "Championship Group", "away_team": "Panathinaikos", "market": "classic", "competition_cluster": "Greece", "prediction": "1X", "status": "pending", "federation": "UEFA", "is_expired": false, "season": "2024 - 2025", "id": 352322, "result": "", "start_date": "2025-04-27T18:00:00", "last_update_at": "2025-04-27T05:41:30.075874", "odds": {"1": 1.965, "X": 3.417, "2": 3.707, "1X": 1.25, "X2": 1.795, "12": 1.29}}, {"home_team": "Nasaf Qarshi", "competition_name": "Super League", "away_team": "PFK Qizilqum", "market": "classic", "competition_cluster": "Uzbekistan", "prediction": "1", "status": "pending", "federation": "AFC", "is_expired": false, "season": "2025", "id": 352566, "result": "", "start_date": "2025-04-27T16:15:00", "last_update_at": "2025-04-27T05:41:30.075874", "odds": {"1": 1.59, "X": 3.332, "2": 5.677, "1X": 1.11, "X2": 2.173, "12": 1.27}}, {"home_team": "Kyzylzhar Petropavl", "competition_name": "Premier League", "away_team": "Kaisar Kyzylorda", "market": "classic", "competition_cluster": "Kazakhstan", "prediction": "12", "status": "pending", "federation": "UEFA", "is_expired": false, "season": "2025", "id": 352333, "result": "", "start_date": "2025-04-27T11:00:00", "last_update_at": "2025-04-27T05:41:30.075874", "odds": {"1": 1.845, "X": 3.15, "2": 4.145, "1X": 1.197, "X2": 1.83, "12": 1.303}}, {"home_team": "KAA Gent", "competition_name": "Championship Group", "away_team": "Anderlecht", "market": "classic", "competition_cluster": "Belgium", "prediction": "12", "status": "pending", "federation": "UEFA", "is_expired": false, "season": "2024 - 2025", "id": 352291, "result": "", "start_date": "2025-04-27T12:30:00", "last_update_at": "2025-04-27T05:41:30.075874", "odds": {"1": 3.035, "X": 3.2, "2": 2.352, "1X": 1.56, "X2": 1.36, "12": 1.327}}, {"home_team": "Shakhtar Donetsk", "competition_name": "Premier League", "away_team": "Dinamo Kiev", "market": "classic", "competition_cluster": "Ukraine", "prediction": "1X", "status": "pending", "federation": "UEFA", "is_expired": false, "season": "2024 - 2025", "id": 352447, "result": "", "start_date": "2025-04-27T16:00:00", "last_update_at": "2025-04-27T05:41:30.075874", "odds": {"1": 2.152, "X": 3.237, "2": 3.225, "1X": 1.305, "X2": 1.643, "12": 1.308}}, {"home_team": "Vorskla Poltava", "competition_name": "Premier League", "away_team": "Veres Rivne", "market": "classic", "competition_cluster": "Ukraine", "prediction": "1X", "status": "pending", "federation": "UEFA", "is_expired": false, "season": "2024 - 2025", "id": 352445, "result": "", "start_date": "2025-04-27T11:00:00", "last_update_at": "2025-04-27T05:41:30.075874", "odds": {"1": 2.338, "X": 3.088, "2": 3.027, "1X": 1.352, "X2": 1.558, "12": 1.332}}, {"home_team": "Flora Tallinn", "competition_name": "Meistriliiga", "away_team": "Nomme Kalju", "market": "classic", "competition_cluster": "Estonia", "prediction": "12", "status": "pending", "federation": "UEFA", "is_expired": false, "season": "2025", "id": 352312, "result": "", "start_date": "2025-04-27T12:30:00", "last_update_at": "2025-04-27T05:41:30.075874", "odds": {"1": 2.002, "X": 3.314, "2": 3.206, "1X": 1.278, "X2": 1.712, "12": 1.28}}, {"home_team": "FC Tyumen", "competition_name": "First League", "away_team": "Neftekhimik Nizhnekamsk", "market": "classic", "competition_cluster": "Russia", "prediction": "1X", "status": "pending", "federation": "UEFA", "is_expired": false, "season": "2024 - 2025", "id": 352402, "result": "", "start_date": "2025-04-27T13:00:00", "last_update_at": "2025-04-27T05:41:30.075874", "odds": {"1": 2.665, "X": 2.935, "2": 2.74, "1X": 1.385, "X2": 1.425, "12": 1.35}}, {"home_team": "Radomiak Radom", "competition_name": "Ekstraklasa", "away_team": "Lech Poznan", "market": "classic", "competition_cluster": "Poland", "prediction": "2", "status": "pending", "federation": "UEFA", "is_expired": false, "season": "2024 - 2025", "id": 352384, "result": "", "start_date": "2025-04-27T16:30:00", "last_update_at": "2025-04-27T05:41:30.075874", "odds": {"1": 3.522, "X": 3.533, "2": 1.98, "1X": 1.78, "X2": 1.267, "12": 1.287}}, {"home_team": "Persija Jakarta", "competition_name": "Liga 1", "away_team": "Semen Padang", "market": "classic", "competition_cluster": "Indonesia", "prediction": "1", "status": "pending", "federation": "AFC", "is_expired": false, "season": "2024 - 2025", "id": 352516, "result": "", "start_date": "2025-04-27T13:00:00", "last_update_at": "2025-04-27T05:41:30.075874", "odds": {"1": 1.37, "X": 4.35, "2": 6.534, "1X": 1.078, "X2": 2.754, "12": 1.166}}, {"home_team": "Milan Futuro", "competition_name": "Serie C", "away_team": "Vis Pesaro 1898", "market": "classic", "competition_cluster": "Italy", "prediction": "1X", "status": "pending", "federation": "UEFA", "is_expired": false, "season": "2024 - 2025", "id": 352251, "result": "", "start_date": "2025-04-27T15:30:00", "last_update_at": "2025-04-27T05:41:30.075874", "odds": {"1": 2.053, "X": 3.11, "2": 3.31, "1X": 1.253, "X2": 1.648, "12": 1.31}}, {"home_team": "Chrobry Glogow", "competition_name": "First League", "away_team": "Miedz Legnica", "market": "classic", "competition_cluster": "Poland", "prediction": "2", "status": "pending", "federation": "UEFA", "is_expired": false, "season": "2024 - 2025", "id": 352387, "result": "", "start_date": "2025-04-27T16:00:00", "last_update_at": "2025-04-27T05:41:30.075874", "odds": {"1": 3.793, "X": 3.3, "2": 1.902, "1X": 1.808, "X2": 1.208, "12": 1.298}}, {"home_team": "Dinamo Zagreb", "competition_name": "Prva HNL", "away_team": "HNK Rijeka", "market": "classic", "competition_cluster": "Croatia", "prediction": "1", "status": "pending", "federation": "UEFA", "is_expired": false, "season": "2024 - 2025", "id": 352300, "result": "", "start_date": "2025-04-27T17:45:00", "last_update_at": "2025-04-27T05:41:30.075874", "odds": {"1": 1.707, "X": 3.358, "2": 4.8, "1X": 1.155, "X2": 2.023, "12": 1.278}}, {"home_team": "Nacional Potosi", "competition_name": "Primera Division", "away_team": "Jorge Wilstermann", "market": "classic", "competition_cluster": "Bolivia", "prediction": "1", "status": "pending", "federation": "CONMEBOL", "is_expired": false, "season": "2025", "id": 352473, "result": "", "start_date": "2025-04-27T20:00:00", "last_update_at": "2025-04-27T05:41:30.075874", "odds": {"1": 1.478, "X": 4.183, "2": 5.807, "1X": 1.107, "X2": 2.463, "12": 1.187}}, {"home_team": "Real Madrid Castilla", "competition_name": "Primera Division RFEF Group 2", "away_team": "Ceuta", "market": "classic", "competition_cluster": "Spain", "prediction": "1X", "status": "pending", "federation": "UEFA", "is_expired": false, "season": "2024 - 2025", "id": 352267, "result": "", "start_date": "2025-04-27T11:00:00", "last_update_at": "2025-04-27T05:41:30.075874", "odds": {"1": 2.285, "X": 3.017, "2": 2.898, "1X": 1.338, "X2": 1.522, "12": 1.308}}, {"home_team": "Bournemouth", "competition_name": "Premier League", "away_team": "Manchester United", "market": "classic", "competition_cluster": "England", "prediction": "1", "status": "pending", "federation": "UEFA", "is_expired": false, "season": "2024 - 2025", "id": 352223, "result": "", "start_date": "2025-04-27T14:00:00", "last_update_at": "2025-04-27T05:41:30.075874", "odds": {"1": 1.708, "X": 4.08, "2": 4.582, "1X": 1.188, "X2": 2.115, "12": 1.227}}, {"home_team": "Skenderbeu Korce", "competition_name": "Superliga", "away_team": "Bylis Ballsh", "market": "classic", "competition_cluster": "Albania", "prediction": "12", "status": "pending", "federation": "UEFA", "is_expired": false, "season": "2024 - 2025", "id": 352274, "result": "", "start_date": "2025-04-27T14:30:00", "last_update_at": "2025-04-27T05:41:30.075874", "odds": {"1": 1.92, "X": 3.23, "2": 3.603, "1X": 1.195, "X2": 1.7, "12": 1.265}}, {"home_team": "IFK Varnamo", "competition_name": "Allsvenskan", "away_team": "Norrkoping", "market": "classic", "competition_cluster": "Sweden", "prediction": "12", "status": "pending", "federation": "UEFA", "is_expired": false, "season": "2025", "id": 352419, "result": "", "start_date": "2025-04-27T15:30:00", "last_update_at": "2025-04-27T05:41:30.075874", "odds": {"1": 2.288, "X": 3.513, "2": 2.913, "1X": 1.385, "X2": 1.583, "12": 1.283}}, {"home_team": "Differdange FC", "competition_name": "National Division", "away_team": "US Hostert", "market": "classic", "competition_cluster": "Luxembourg", "prediction": "1", "status": "pending", "federation": "UEFA", "is_expired": false, "season": "2024 - 2025", "id": 352339, "result": "", "start_date": "2025-04-27T15:00:00", "last_update_at": "2025-04-27T05:41:30.075874", "odds": {"1": 1.15, "X": 6.625, "2": 12.475, "1X": 1.027, "X2": 4.267, "12": 1.067}}, {"home_team": "Antigua GFC", "competition_name": "Liga Nacional", "away_team": "Deportivo Achuapa", "market": "classic", "competition_cluster": "Guatemala", "prediction": "1", "status": "pending", "federation": "CONCACAF", "is_expired": false, "season": "2025 - Clausura", "id": 352586, "result": "", "start_date": "2025-04-27T22:00:00", "last_update_at": "2025-04-27T05:41:30.075874", "odds": {"1": 1.36, "X": 4.3, "2": 7.037, "1X": 1.063, "X2": 2.75, "12": 1.16}}, {"home_team": "Sirius", "competition_name": "Allsvenskan", "away_team": "Halmstads", "market": "classic", "competition_cluster": "Sweden", "prediction": "1", "status": "pending", "federation": "UEFA", "is_expired": false, "season": "2025", "id": 352420, "result": "", "start_date": "2025-04-27T15:30:00", "last_update_at": "2025-04-27T05:41:30.075874", "odds": {"1": 1.562, "X": 4.067, "2": 5.642, "1X": 1.135, "X2": 2.342, "12": 1.218}}, {"home_team": "Trapani", "competition_name": "Serie C", "away_team": "Casertana", "market": "classic", "competition_cluster": "Italy", "prediction": "12", "status": "pending", "federation": "UEFA", "is_expired": false, "season": "2024 - 2025", "id": 352734, "result": "", "start_date": "2025-04-27T19:00:00", "last_update_at": "2025-04-27T05:41:30.075874", "odds": {"1": 2.308, "X": 3.016, "2": 2.884, "1X": 1.326, "X2": 1.514, "12": 1.306}}, {"home_team": "Al-Jazira Abu Dhabi", "competition_name": "Pro-League", "away_team": "Al Sharjah SC", "market": "classic", "competition_cluster": "UAE", "prediction": "2", "status": "pending", "federation": "AFC", "is_expired": false, "season": "2024 - 2025", "id": 352550, "result": "", "start_date": "2025-04-27T15:00:00", "last_update_at": "2025-04-27T05:41:30.075874", "odds": {"1": 3.49, "X": 3.723, "2": 1.837, "1X": 1.83, "X2": 1.235, "12": 1.21}}, {"home_team": "Kayserispor", "competition_name": "Super Lig", "away_team": "Caykur Rizespor", "market": "classic", "competition_cluster": "Turkey", "prediction": "12", "status": "pending", "federation": "UEFA", "is_expired": false, "season": "2024 - 2025", "id": 352434, "result": "", "start_date": "2025-04-27T17:00:00", "last_update_at": "2025-04-27T05:41:30.075874", "odds": {"1": 2.242, "X": 3.182, "2": 3.247, "1X": 1.323, "X2": 1.623, "12": 1.337}}, {"home_team": "Manama Club", "competition_name": "Premier League", "away_team": "Al-Ahli Manama", "market": "classic", "competition_cluster": "Bahrain", "prediction": "12", "status": "pending", "federation": "AFC", "is_expired": false, "season": "2024 - 2025", "id": 352470, "result": "", "start_date": "2025-04-27T17:20:00", "last_update_at": "2025-04-27T05:41:30.075874", "odds": {"1": 2.79, "X": 2.973, "2": 2.378, "1X": 1.47, "X2": 1.357, "12": 1.317}}, {"home_team": "Sportivo Luqueno", "competition_name": "Primera Division", "away_team": "General Caballero JLM", "market": "classic", "competition_cluster": "Paraguay", "prediction": "1X", "status": "pending", "federation": "CONMEBOL", "is_expired": false, "season": "2025 - Apertura", "id": 352595, "result": "", "start_date": "2025-04-27T22:00:00", "last_update_at": "2025-04-27T05:41:30.075874", "odds": {"1": 2.35, "X": 3.038, "2": 2.893, "1X": 1.363, "X2": 1.52, "12": 1.33}}, {"home_team": "Kristiansund", "competition_name": "Eliteserien", "away_team": "Valerenga Oslo", "market": "classic", "competition_cluster": "Norway", "prediction": "2", "status": "pending", "federation": "UEFA", "is_expired": false, "season": "2025", "id": 352363, "result": "", "start_date": "2025-04-27T16:00:00", "last_update_at": "2025-04-27T05:41:30.075874", "odds": {"1": 3.212, "X": 3.56, "2": 2.098, "1X": 1.683, "X2": 1.328, "12": 1.278}}, {"home_team": "FC Midtjylland", "competition_name": "Championship Group", "away_team": "FC Nordsjaelland", "market": "classic", "competition_cluster": "Denmark", "prediction": "12", "status": "pending", "federation": "UEFA", "is_expired": false, "season": "2024 - 2025", "id": 352308, "result": "", "start_date": "2025-04-27T17:00:00", "last_update_at": "2025-04-27T05:41:30.075874", "odds": {"1": 2.0, "X": 3.888, "2": 3.21, "1X": 1.317, "X2": 1.768, "12": 1.235}}, {"home_team": "Inter Miami", "competition_name": "Major League Soccer", "away_team": "FC Dallas", "market": "classic", "competition_cluster": "USA", "prediction": "1", "status": "pending", "federation": "CONCACAF", "is_expired": false, "season": "2025", "id": 352597, "result": "", "start_date": "2025-04-27T22:00:00", "last_update_at": "2025-04-27T05:41:30.075874", "odds": {"1": 1.695, "X": 4.05, "2": 4.437, "1X": 1.19, "X2": 2.107, "12": 1.22}}, {"home_team": "NK Osijek", "competition_name": "Prva HNL", "away_team": "Hajduk Split", "market": "classic", "competition_cluster": "Croatia", "prediction": "2", "status": "pending", "federation": "UEFA", "is_expired": false, "season": "2024 - 2025", "id": 352299, "result": "", "start_date": "2025-04-27T15:00:00", "last_update_at": "2025-04-27T05:41:30.075874", "odds": {"1": 3.997, "X": 3.265, "2": 1.865, "1X": 1.845, "X2": 1.205, "12": 1.293}}, {"home_team": "Shirak", "competition_name": "Premier League", "away_team": "Urartu", "market": "classic", "competition_cluster": "Armenia", "prediction": "2", "status": "pending", "federation": "UEFA", "is_expired": false, "season": "2024 - 2025", "id": 352282, "result": "", "start_date": "2025-04-27T16:00:00", "last_update_at": "2025-04-27T05:41:30.075874", "odds": {"1": 4.18, "X": 3.655, "2": 1.675, "1X": 2.017, "X2": 1.17, "12": 1.21}}, {"home_team": "Zalaegerszegi", "competition_name": "NB I", "away_team": "Kecskemeti", "market": "classic", "competition_cluster": "Hungary", "prediction": "12", "status": "pending", "federation": "UEFA", "is_expired": false, "season": "2024 - 2025", "id": 352328, "result": "", "start_date": "2025-04-27T17:00:00", "last_update_at": "2025-04-27T05:41:30.075874", "odds": {"1": 1.948, "X": 3.118, "2": 3.905, "1X": 1.222, "X2": 1.772, "12": 1.32}}, {"home_team": "Napoli", "competition_name": "Serie A", "away_team": "Torino", "market": "classic", "competition_cluster": "Italy", "prediction": "1", "status": "pending", "federation": "UEFA", "is_expired": false, "season": "2024 - 2025", "id": 352246, "result": "", "start_date": "2025-04-27T19:45:00", "last_update_at": "2025-04-27T05:41:30.075874", "odds": {"1": 1.408, "X": 4.525, "2": 8.408, "1X": 1.067, "X2": 2.873, "12": 1.19}}, {"home_team": "Fortaleza CEIF", "competition_name": "Categoria Primera A", "away_team": "Independiente Medellin", "market": "classic", "competition_cluster": "Colombia", "prediction": "2", "status": "pending", "federation": "CONMEBOL", "is_expired": false, "season": "2025 - Apertura", "id": 352584, "result": "", "start_date": "2025-04-27T22:10:00", "last_update_at": "2025-04-27T05:41:30.075874", "odds": {"1": 4.74, "X": 3.497, "2": 1.72, "1X": 2.012, "X2": 1.168, "12": 1.268}}, {"home_team": "Ordabasy Shymkent", "competition_name": "Premier League", "away_team": "Turan Turkistan", "market": "classic", "competition_cluster": "Kazakhstan", "prediction": "1", "status": "pending", "federation": "UEFA", "is_expired": false, "season": "2025", "id": 352335, "result": "", "start_date": "2025-04-27T12:00:00", "last_update_at": "2025-04-27T05:41:30.075874", "odds": {"1": 1.418, "X": 3.97, "2": 7.088, "1X": 1.077, "X2": 2.59, "12": 1.203}}, {"home_team": "Fiorentina", "competition_name": "Serie A", "away_team": "Empoli", "market": "classic", "competition_cluster": "Italy", "prediction": "1", "status": "pending", "federation": "UEFA", "is_expired": false, "season": "2024 - 2025", "id": 352243, "result": "", "start_date": "2025-04-27T14:00:00", "last_update_at": "2025-04-27T05:41:30.075874", "odds": {"1": 1.84, "X": 3.482, "2": 4.64, "1X": 1.178, "X2": 1.943, "12": 1.293}}, {"home_team": "Dinamo Minsk", "competition_name": "Premier League", "away_team": "FC Minsk", "market": "classic", "competition_cluster": "Belarus", "prediction": "1", "status": "pending", "federation": "UEFA", "is_expired": false, "season": "2025", "id": 352290, "result": "", "start_date": "2025-04-27T18:00:00", "last_update_at": "2025-04-27T05:41:30.075874", "odds": {"1": 1.417, "X": 4.183, "2": 6.7, "1X": 1.083, "X2": 2.713, "12": 1.19}}, {"home_team": "Atletico Grau", "competition_name": "Liga 1", "away_team": "Sport Boys", "market": "classic", "competition_cluster": "Peru", "prediction": "1", "status": "pending", "federation": "CONMEBOL", "is_expired": false, "season": "2025 - Apertura", "id": 352536, "result": "", "start_date": "2025-04-27T21:30:00", "last_update_at": "2025-04-27T05:41:30.075874", "odds": {"1": 1.742, "X": 3.34, "2": 4.888, "1X": 1.164, "X2": 1.99, "12": 1.298}}, {"home_team": "Sotra SK", "competition_name": "2. Division", "away_team": "Notodden", "market": "classic", "competition_cluster": "Norway", "prediction": "1", "status": "pending", "federation": "UEFA", "is_expired": false, "season": "2025", "id": 352371, "result": "", "start_date": "2025-04-27T12:00:00", "last_update_at": "2025-04-27T05:41:30.075874", "odds": {"1": 1.564, "X": 3.744, "2": 4.892, "1X": 1.13, "X2": 2.193, "12": 1.21}}, {"home_team": "Umea FC", "competition_name": "Superettan", "away_team": "Brage", "market": "classic", "competition_cluster": "Sweden", "prediction": "2", "status": "pending", "federation": "UEFA", "is_expired": false, "season": "2025", "id": 352423, "result": "", "start_date": "2025-04-27T12:00:00", "last_update_at": "2025-04-27T05:41:30.075874", "odds": {"1": 3.198, "X": 3.383, "2": 2.087, "1X": 1.678, "X2": 1.32, "12": 1.293}}, {"home_team": "NK Celje", "competition_name": "1. SNL", "away_team": "Olimpija Ljubljana", "market": "classic", "competition_cluster": "Slovenia", "prediction": "1X", "status": "pending", "federation": "UEFA", "is_expired": false, "season": "2024 - 2025", "id": 352415, "result": "", "start_date": "2025-04-27T16:30:00", "last_update_at": "2025-04-27T05:41:30.075874", "odds": {"1": 2.508, "X": 3.126, "2": 2.624, "1X": 1.418, "X2": 1.45, "12": 1.325}}, {"home_team": "KR Reykjavik", "competition_name": "Premier League", "away_team": "Akranes", "market": "classic", "competition_cluster": "Iceland", "prediction": "12", "status": "pending", "federation": "UEFA", "is_expired": false, "season": "2025", "id": 352331, "result": "", "start_date": "2025-04-27T20:15:00", "last_update_at": "2025-04-27T05:41:30.075874", "odds": {"1": 1.922, "X": 3.93, "2": 3.158, "1X": 1.31, "X2": 1.778, "12": 1.208}}, {"home_team": "Lucchese", "competition_name": "Serie C", "away_team": "Torres", "market": "classic", "competition_cluster": "Italy", "prediction": "1X", "status": "pending", "federation": "UEFA", "is_expired": false, "season": "2024 - 2025", "id": 352250, "result": "", "start_date": "2025-04-27T15:30:00", "last_update_at": "2025-04-27T05:41:30.075874", "odds": {"1": 1.866, "X": 3.208, "2": 3.74, "1X": 1.204, "X2": 1.806, "12": 1.266}}, {"home_team": "Sarpsborg 08", "competition_name": "Eliteserien", "away_team": "Stromsgodset", "market": "classic", "competition_cluster": "Norway", "prediction": "12", "status": "pending", "federation": "UEFA", "is_expired": false, "season": "2025", "id": 352365, "result": "", "start_date": "2025-04-27T16:00:00", "last_update_at": "2025-04-27T05:41:30.075874", "odds": {"1": 1.9, "X": 3.905, "2": 3.515, "1X": 1.28, "X2": 1.84, "12": 1.233}}, {"home_team": "Suduva Marijampole", "competition_name": "A Lyga", "away_team": "Hegelmann Kaunas", "market": "classic", "competition_cluster": "Lithuania", "prediction": "2", "status": "pending", "federation": "UEFA", "is_expired": false, "season": "2025", "id": 352338, "result": "", "start_date": "2025-04-27T16:25:00", "last_update_at": "2025-04-27T05:41:30.075874", "odds": {"1": 3.542, "X": 3.252, "2": 1.932, "1X": 1.78, "X2": 1.242, "12": 1.27}}, {"home_team": "Rimini", "competition_name": "Serie C", "away_team": "Pineto", "market": "classic", "competition_cluster": "Italy", "prediction": "1", "status": "pending", "federation": "UEFA", "is_expired": false, "season": "2024 - 2025", "id": 352255, "result": "", "start_date": "2025-04-27T15:30:00", "last_update_at": "2025-04-27T05:41:30.075874", "odds": {"1": 1.686, "X": 3.458, "2": 4.316, "1X": 1.17, "X2": 1.99, "12": 1.232}}, {"home_team": "Ajax Amsterdam", "competition_name": "Eredivisie", "away_team": "Sparta Rotterdam", "market": "classic", "competition_cluster": "Netherlands", "prediction": "1", "status": "pending", "federation": "UEFA", "is_expired": false, "season": "2024 - 2025", "id": 352350, "result": "", "start_date": "2025-04-27T13:30:00", "last_update_at": "2025-04-27T05:41:30.075874", "odds": {"1": 1.448, "X": 4.783, "2": 6.233, "1X": 1.108, "X2": 2.692, "12": 1.173}}, {"home_team": "Sudtirol", "competition_name": "Serie B", "away_team": "Juve Stabia", "market": "classic", "competition_cluster": "Italy", "prediction": "1X", "status": "pending", "federation": "UEFA", "is_expired": false, "season": "2024 - 2025", "id": 352725, "result": "", "start_date": "2025-04-27T14:00:00", "last_update_at": "2025-04-27T05:41:30.075874", "odds": {"1": 2.543, "X": 2.96, "2": 2.955, "1X": 1.372, "X2": 1.487, "12": 1.382}}, {"home_team": "Racing FC Union", "competition_name": "National Division", "away_team": "Jeunesse Esch", "market": "classic", "competition_cluster": "Luxembourg", "prediction": "1", "status": "pending", "federation": "UEFA", "is_expired": false, "season": "2024 - 2025", "id": 352342, "result": "", "start_date": "2025-04-27T15:00:00", "last_update_at": "2025-04-27T05:41:30.075874", "odds": {"1": 1.495, "X": 3.987, "2": 5.16, "1X": 1.11, "X2": 2.337, "12": 1.18}}, {"home_team": "Entella", "competition_name": "Serie C", "away_team": "Ternana", "market": "classic", "competition_cluster": "Italy", "prediction": "1X", "status": "pending", "federation": "UEFA", "is_expired": false, "season": "2024 - 2025", "id": 352249, "result": "", "start_date": "2025-04-27T15:30:00", "last_update_at": "2025-04-27T05:41:30.075874", "odds": {"1": 2.178, "X": 2.922, "2": 3.174, "1X": 1.266, "X2": 1.568, "12": 1.34}}, {"home_team": "Messina", "competition_name": "Serie C", "away_team": "Juventus Next Gen", "market": "classic", "competition_cluster": "Italy", "prediction": "12", "status": "pending", "federation": "UEFA", "is_expired": false, "season": "2024 - 2025", "id": 352731, "result": "", "start_date": "2025-04-27T19:00:00", "last_update_at": "2025-04-27T05:41:30.075874", "odds": {"1": 1.94, "X": 3.197, "2": 3.51, "1X": 1.225, "X2": 1.7, "12": 1.26}}, {"home_team": "Audace Cerignola", "competition_name": "Serie C", "away_team": "Latina", "market": "classic", "competition_cluster": "Italy", "prediction": "1", "status": "pending", "federation": "UEFA", "is_expired": false, "season": "2024 - 2025", "id": 352727, "result": "", "start_date": "2025-04-27T19:00:00", "last_update_at": "2025-04-27T05:41:30.075874", "odds": {"1": 1.352, "X": 4.53, "2": 6.42, "1X": 1.06, "X2": 2.782, "12": 1.146}}, {"home_team": "Comunicaciones", "competition_name": "Liga Nacional", "away_team": "Xinabajul", "market": "classic", "competition_cluster": "Guatemala", "prediction": "1", "status": "pending", "federation": "CONCACAF", "is_expired": false, "season": "2025 - Clausura", "id": 352588, "result": "", "start_date": "2025-04-27T22:00:00", "last_update_at": "2025-04-27T05:41:30.075874", "odds": {"1": 1.357, "X": 4.312, "2": 7.137, "1X": 1.06, "X2": 2.75, "12": 1.16}}, {"home_team": "Montevideo City Torque", "competition_name": "Primera Division", "away_team": "Defensor Sporting", "market": "classic", "competition_cluster": "Uruguay", "prediction": "1X", "status": "pending", "federation": "CONMEBOL", "is_expired": false, "season": "2025 - Apertura", "id": 352553, "result": "", "start_date": "2025-04-27T14:45:00", "last_update_at": "2025-04-27T05:41:30.075874", "odds": {"1": 2.758, "X": 3.192, "2": 2.428, "1X": 1.493, "X2": 1.395, "12": 1.305}}, {"home_team": "Werder Bremen", "competition_name": "Bundesliga", "away_team": "Sankt Pauli", "market": "classic", "competition_cluster": "Germany", "prediction": "12", "status": "pending", "federation": "UEFA", "is_expired": false, "season": "2024 - 2025", "id": 352234, "result": "", "start_date": "2025-04-27T16:30:00", "last_update_at": "2025-04-27T05:41:30.075874", "odds": {"1": 1.923, "X": 3.622, "2": 3.978, "1X": 1.238, "X2": 1.865, "12": 1.283}}, {"home_team": "Lens", "competition_name": "Ligue 1", "away_team": "Auxerre", "market": "classic", "competition_cluster": "France", "prediction": "1", "status": "pending", "federation": "UEFA", "is_expired": false, "season": "2024 - 2025", "id": 352229, "result": "", "start_date": "2025-04-27T16:15:00", "last_update_at": "2025-04-27T05:41:30.075874", "odds": {"1": 1.542, "X": 4.448, "2": 5.77, "1X": 1.13, "X2": 2.443, "12": 1.202}}, {"home_team": "Picerno", "competition_name": "Serie C", "away_team": "Foggia", "market": "classic", "competition_cluster": "Italy", "prediction": "1X", "status": "pending", "federation": "UEFA", "is_expired": false, "season": "2024 - 2025", "id": 352732, "result": "", "start_date": "2025-04-27T19:00:00", "last_update_at": "2025-04-27T05:41:30.075874", "odds": {"1": 2.08, "X": 3.014, "2": 3.272, "1X": 1.244, "X2": 1.62, "12": 1.318}}, {"home_team": "Excelsior", "competition_name": "Eerste Divisie", "away_team": "FC Emmen", "market": "classic", "competition_cluster": "Netherlands", "prediction": "1", "status": "pending", "federation": "UEFA", "is_expired": false, "season": "2024 - 2025", "id": 352353, "result": "", "start_date": "2025-04-27T15:45:00", "last_update_at": "2025-04-27T05:41:30.075874", "odds": {"1": 1.477, "X": 4.463, "2": 5.638, "1X": 1.12, "X2": 2.553, "12": 1.183}}, {"home_team": "Vitoria Guimaraes", "competition_name": "Primeira Liga", "away_team": "Rio Ave", "market": "classic", "competition_cluster": "Portugal", "prediction": "1", "status": "pending", "federation": "UEFA", "is_expired": false, "season": "2024 - 2025", "id": 352390, "result": "", "start_date": "2025-04-27T18:00:00", "last_update_at": "2025-04-27T05:41:30.075874", "odds": {"1": 1.487, "X": 4.225, "2": 6.242, "1X": 1.107, "X2": 2.553, "12": 1.205}}, {"home_team": "Minnesota United", "competition_name": "Major League Soccer", "away_team": "Vancouver Whitecaps", "market": "classic", "competition_cluster": "USA", "prediction": "1X", "status": "pending", "federation": "CONCACAF", "is_expired": false, "season": "2025", "id": 352563, "result": "", "start_date": "2025-04-27T20:00:00", "last_update_at": "2025-04-27T05:41:30.075874", "odds": {"1": 1.992, "X": 3.435, "2": 3.7, "1X": 1.262, "X2": 1.763, "12": 1.283}}, {"home_team": "Hoang Anh Gia Lai", "competition_name": "V.League 1", "away_team": "Hai Phong", "market": "classic", "competition_cluster": "Vietnam", "prediction": "1", "status": "pending", "federation": "AFC", "is_expired": false, "season": "2024 - 2025", "id": 352568, "result": "", "start_date": "2025-04-27T11:00:00", "last_update_at": "2025-04-27T05:41:30.075874", "odds": {"1": 1.675, "X": 3.4, "2": 4.54, "1X": 1.145, "X2": 2.005, "12": 1.245}}, {"home_team": "Zamora CF", "competition_name": "Primera Division RFEF Group 1", "away_team": "Celta Fortuna", "market": "classic", "competition_cluster": "Spain", "prediction": "1X", "status": "pending", "federation": "UEFA", "is_expired": false, "season": "2024 - 2025", "id": 352266, "result": "", "start_date": "2025-04-27T18:30:00", "last_update_at": "2025-04-27T05:41:30.075874", "odds": {"1": 2.22, "X": 3.073, "2": 2.953, "1X": 1.342, "X2": 1.55, "12": 1.298}}, {"home_team": "Waldhof Mannheim", "competition_name": "3. Liga", "away_team": "Stuttgart II", "market": "classic", "competition_cluster": "Germany", "prediction": "12", "status": "pending", "federation": "UEFA", "is_expired": false, "season": "2024 - 2025", "id": 352240, "result": "", "start_date": "2025-04-27T18:30:00", "last_update_at": "2025-04-27T05:41:30.075874", "odds": {"1": 1.988, "X": 3.492, "2": 3.372, "1X": 1.282, "X2": 1.758, "12": 1.26}}, {"home_team": "Flamengo RJ", "competition_name": "Serie A", "away_team": "Corinthians SP", "market": "classic", "competition_cluster": "Brazil", "prediction": "1", "status": "pending", "federation": "CONMEBOL", "is_expired": false, "season": "2025", "id": 352476, "result": "", "start_date": "2025-04-27T20:00:00", "last_update_at": "2025-04-27T05:41:30.075874", "odds": {"1": 1.46, "X": 4.188, "2": 7.192, "1X": 1.087, "X2": 2.642, "12": 1.207}}, {"home_team": "Feirense", "competition_name": "Liga Portugal 2", "away_team": "Porto B", "market": "classic", "competition_cluster": "Portugal", "prediction": "1X", "status": "pending", "federation": "UEFA", "is_expired": false, "season": "2024 - 2025", "id": 352392, "result": "", "start_date": "2025-04-27T11:00:00", "last_update_at": "2025-04-27T05:41:30.075874", "odds": {"1": 2.543, "X": 3.092, "2": 2.665, "1X": 1.417, "X2": 1.465, "12": 1.328}}, {"home_team": "Uthai Thani", "competition_name": "Thai League 1", "away_team": "Lamphun Warriors", "market": "classic", "competition_cluster": "Thailand", "prediction": "1X", "status": "pending", "federation": "AFC", "is_expired": false, "season": "2024 - 2025", "id": 352547, "result": "", "start_date": "2025-04-27T12:00:00", "last_update_at": "2025-04-27T05:41:30.075874", "odds": {"1": 2.3, "X": 3.148, "2": 2.718, "1X": 1.375, "X2": 1.53, "12": 1.288}}, {"home_team": "Ascoli", "competition_name": "Serie C", "away_team": "Legnago Salus", "market": "classic", "competition_cluster": "Italy", "prediction": "1X", "status": "pending", "federation": "UEFA", "is_expired": false, "season": "2024 - 2025", "id": 352247, "result": "", "start_date": "2025-04-27T15:30:00", "last_update_at": "2025-04-27T05:41:30.075874", "odds": {"1": 1.85, "X": 3.492, "2": 3.512, "1X": 1.23, "X2": 1.818, "12": 1.246}}, {"home_team": "NK GOSK Gabela", "competition_name": "Premier League", "away_team": "Velez Mostar", "market": "classic", "competition_cluster": "Bosnia and Herzegovina", "prediction": "2", "status": "pending", "federation": "UEFA", "is_expired": false, "season": "2024 - 2025", "id": 351927, "result": "", "start_date": "2025-04-27T16:30:00", "last_update_at": "2025-04-27T05:41:30.075874", "odds": {"1": 7.95, "X": 3.987, "2": 1.378, "1X": 2.733, "X2": 1.047, "12": 1.2}}, {"home_team": "Al-Khalidiya", "competition_name": "Premier League", "away_team": "Al-Muharraq", "market": "classic", "competition_cluster": "Bahrain", "prediction": "1X", "status": "pending", "federation": "AFC", "is_expired": false, "season": "2024 - 2025", "id": 352469, "result": "", "start_date": "2025-04-27T17:20:00", "last_update_at": "2025-04-27T05:41:30.075874", "odds": {"1": 2.068, "X": 3.18, "2": 3.182, "1X": 1.28, "X2": 1.63, "12": 1.287}}, {"home_team": "Inter Club d'Escaldes", "competition_name": "Primera Divisio", "away_team": "Pas de la Casa", "market": "classic", "competition_cluster": "Andorra", "prediction": "1", "status": "pending", "federation": "UEFA", "is_expired": false, "season": "2024 - 2025", "id": 352281, "result": "", "start_date": "2025-04-27T17:30:00", "last_update_at": "2025-04-27T05:41:30.075874", "odds": {"1": 1.16, "X": 6.117, "2": 10.967, "1X": 1.005, "X2": 3.975, "12": 1.06}}, {"home_team": "York United", "competition_name": "Premier League", "away_team": "Forge FC", "market": "classic", "competition_cluster": "Canada", "prediction": "12", "status": "pending", "federation": "CONCACAF", "is_expired": false, "season": "2025", "id": 352494, "result": "", "start_date": "2025-04-27T19:00:00", "last_update_at": "2025-04-27T05:41:30.075874", "odds": {"1": 2.698, "X": 3.13, "2": 2.34, "1X": 1.487, "X2": 1.383, "12": 1.295}}, {"home_team": "Amazonas AM", "competition_name": "Serie B", "away_team": "Atletico GO", "market": "classic", "competition_cluster": "Brazil", "prediction": "1X", "status": "pending", "federation": "CONMEBOL", "is_expired": false, "season": "2025", "id": 352479, "result": "", "start_date": "2025-04-27T20:30:00", "last_update_at": "2025-04-27T05:41:30.075874", "odds": {"1": 2.713, "X": 2.975, "2": 2.667, "1X": 1.442, "X2": 1.423, "12": 1.363}}, {"home_team": "Boavista", "competition_name": "Primeira Liga", "away_team": "Sporting CP", "market": "classic", "competition_cluster": "Portugal", "prediction": "2", "status": "pending", "federation": "UEFA", "is_expired": false, "season": "2024 - 2025", "id": 352391, "result": "", "start_date": "2025-04-27T20:30:00", "last_update_at": "2025-04-27T05:41:30.075874", "odds": {"1": 13.0, "X": 6.583, "2": 1.195, "1X": 4.443, "X2": 1.028, "12": 1.095}}, {"home_team": "O'Higgins Rancagua", "competition_name": "Primera Division", "away_team": "Deportes Iquique", "market": "classic", "competition_cluster": "Chile", "prediction": "12", "status": "pending", "federation": "CONMEBOL", "is_expired": false, "season": "2025", "id": 352496, "result": "", "start_date": "2025-04-27T17:30:00", "last_update_at": "2025-04-27T05:41:30.075874", "odds": {"1": 1.883, "X": 3.647, "2": 3.645, "1X": 1.257, "X2": 1.85, "12": 1.258}}]}
