{"data": [{"season": "2025", "id": 353930, "result": "", "start_date": "2025-05-05T14:00:00", "last_update_at": "2025-05-05T04:49:12.991479", "home_team": "Auda Kekava", "competition_name": "Virsliga", "away_team": "Riga FC", "market": "classic", "competition_cluster": "Latvia", "prediction": "2", "status": "pending", "federation": "UEFA", "is_expired": false, "odds": {"1": 5.224, "X": 3.716, "2": 1.542, "1X": 2.255, "X2": 1.12, "12": 1.22}}, {"season": "2024 - 2025", "id": 353902, "result": "", "start_date": "2025-05-05T15:00:00", "last_update_at": "2025-05-05T04:49:12.991479", "home_team": "Sutton United", "competition_name": "National League", "away_team": "Woking", "market": "classic", "competition_cluster": "England", "prediction": "12", "status": "pending", "federation": "UEFA", "is_expired": false, "odds": {"1": 2.098, "X": 3.42, "2": 2.993, "1X": 1.337, "X2": 1.657, "12": 1.27}}, {"season": "2025", "id": 353921, "result": "", "start_date": "2025-05-05T17:00:00", "last_update_at": "2025-05-05T04:49:12.991479", "home_team": "Galway United FC", "competition_name": "Premier Division", "away_team": "Bohemians", "market": "classic", "competition_cluster": "Ireland", "prediction": "1X", "status": "pending", "federation": "UEFA", "is_expired": false, "odds": {"1": 2.517, "X": 3.112, "2": 2.79, "1X": 1.407, "X2": 1.49, "12": 1.34}}, {"season": "2024 - 2025", "id": 353940, "result": "", "start_date": "2025-05-05T16:30:00", "last_update_at": "2025-05-05T04:49:12.991479", "home_team": "Krylya Sovetov Samara", "competition_name": "Premier League", "away_team": "Dinamo Moskva", "market": "classic", "competition_cluster": "Russia", "prediction": "1X", "status": "pending", "federation": "UEFA", "is_expired": false, "odds": {"1": 2.85, "X": 3.69, "2": 2.4, "1X": 1.585, "X2": 1.43, "12": 1.285}}, {"season": "2024 - 2025", "id": 353899, "result": "", "start_date": "2025-05-05T15:00:00", "last_update_at": "2025-05-05T04:49:12.991479", "home_team": "Maidenhead United", "competition_name": "National League", "away_team": "Boston United", "market": "classic", "competition_cluster": "England", "prediction": "12", "status": "pending", "federation": "UEFA", "is_expired": false, "odds": {"1": 2.022, "X": 3.232, "2": 3.355, "1X": 1.287, "X2": 1.707, "12": 1.305}}, {"season": "2025", "id": 353945, "result": "", "start_date": "2025-05-05T18:00:00", "last_update_at": "2025-05-05T04:49:12.991479", "home_team": "Assyriska Foreningen", "competition_name": "Division 1", "away_team": "Vasalunds IF", "market": "classic", "competition_cluster": "Sweden", "prediction": "2", "status": "pending", "federation": "UEFA", "is_expired": false, "odds": {"1": 2.907, "X": 3.34, "2": 2.183, "1X": 1.585, "X2": 1.33, "12": 1.255}}, {"season": "2024 - 2025", "id": 353895, "result": "", "start_date": "2025-05-05T15:00:00", "last_update_at": "2025-05-05T04:49:12.991479", "home_team": "Eastleigh", "competition_name": "National League", "away_team": "York City", "market": "classic", "competition_cluster": "England", "prediction": "2", "status": "pending", "federation": "UEFA", "is_expired": false, "odds": {"1": 3.913, "X": 3.497, "2": 1.787, "1X": 1.917, "X2": 1.21, "12": 1.262}}, {"season": "2024 - 2025", "id": 353892, "result": "", "start_date": "2025-05-05T15:00:00", "last_update_at": "2025-05-05T04:49:12.991479", "home_team": "Aldershot", "competition_name": "National League", "away_team": "Yeovil", "market": "classic", "competition_cluster": "England", "prediction": "12", "status": "pending", "federation": "UEFA", "is_expired": false, "odds": {"1": 2.133, "X": 3.125, "2": 3.21, "1X": 1.307, "X2": 1.633, "12": 1.317}}, {"season": "2025", "id": 353923, "result": "", "start_date": "2025-05-05T19:00:00", "last_update_at": "2025-05-05T04:49:12.991479", "home_team": "Shamrock Rovers", "competition_name": "Premier Division", "away_team": "Sligo Rovers", "market": "classic", "competition_cluster": "Ireland", "prediction": "1", "status": "pending", "federation": "UEFA", "is_expired": false, "odds": {"1": 1.308, "X": 4.992, "2": 9.042, "1X": 1.057, "X2": 3.298, "12": 1.16}}, {"season": "2025", "id": 353919, "result": "", "start_date": "2025-05-05T20:15:00", "last_update_at": "2025-05-05T04:49:12.991479", "home_team": "Vikingur Reykjavik", "competition_name": "Premier League", "away_team": "Fram Reykjavik", "market": "classic", "competition_cluster": "Iceland", "prediction": "1", "status": "pending", "federation": "UEFA", "is_expired": false, "odds": {"1": 1.344, "X": 5.13, "2": 6.308, "1X": 1.086, "X2": 2.95, "12": 1.126}}, {"season": "2025", "id": 353943, "result": "", "start_date": "2025-05-05T18:00:00", "last_update_at": "2025-05-05T04:49:12.991479", "home_team": "Brage", "competition_name": "Superettan", "away_team": "Ostersunds", "market": "classic", "competition_cluster": "Sweden", "prediction": "1X", "status": "pending", "federation": "UEFA", "is_expired": false, "odds": {"1": 1.925, "X": 3.347, "2": 3.753, "1X": 1.243, "X2": 1.8, "12": 1.297}}, {"season": "2024 - 2025", "id": 353967, "result": "", "start_date": "2025-05-05T13:00:00", "last_update_at": "2025-05-05T04:49:12.991479", "home_team": "Persis Solo", "competition_name": "Liga 1", "away_team": "Arema Malang", "market": "classic", "competition_cluster": "Indonesia", "prediction": "1", "status": "pending", "federation": "AFC", "is_expired": false, "odds": {"1": 1.69, "X": 3.605, "2": 4.155, "1X": 1.175, "X2": 2.025, "12": 1.222}}, {"season": "2024 - 2025", "id": 353979, "result": "", "start_date": "2025-05-05T15:05:00", "last_update_at": "2025-05-05T04:49:12.991479", "home_team": "Al Bataeh Club", "competition_name": "Pro-League", "away_team": "Baniyas SC", "market": "classic", "competition_cluster": "UAE", "prediction": "12", "status": "pending", "federation": "AFC", "is_expired": false, "odds": {"1": 1.883, "X": 3.475, "2": 3.485, "1X": 1.263, "X2": 1.807, "12": 1.233}}, {"season": "2025", "id": 353920, "result": "", "start_date": "2025-05-05T17:00:00", "last_update_at": "2025-05-05T04:49:12.991479", "home_team": "Drogheda United", "competition_name": "Premier Division", "away_team": "Cork City", "market": "classic", "competition_cluster": "Ireland", "prediction": "1X", "status": "pending", "federation": "UEFA", "is_expired": false, "odds": {"1": 1.82, "X": 3.472, "2": 4.247, "1X": 1.2, "X2": 1.938, "12": 1.288}}, {"season": "2025", "id": 353956, "result": "", "start_date": "2025-05-05T12:35:00", "last_update_at": "2025-05-05T04:49:12.991479", "home_team": "Chengdu Rongcheng", "competition_name": "Super League", "away_team": "Zhejiang Professional", "market": "classic", "competition_cluster": "China", "prediction": "1", "status": "pending", "federation": "AFC", "is_expired": false, "odds": {"1": 1.505, "X": 4.537, "2": 5.407, "1X": 1.133, "X2": 2.447, "12": 1.183}}, {"season": "2024 - 2025", "id": 353903, "result": "", "start_date": "2025-05-05T15:00:00", "last_update_at": "2025-05-05T04:49:12.991479", "home_team": "Wealdstone", "competition_name": "National League", "away_team": "Halifax", "market": "classic", "competition_cluster": "England", "prediction": "12", "status": "pending", "federation": "UEFA", "is_expired": false, "odds": {"1": 1.998, "X": 3.368, "2": 3.25, "1X": 1.298, "X2": 1.72, "12": 1.282}}, {"season": "2024 - 2025", "id": 353898, "result": "", "start_date": "2025-05-05T15:00:00", "last_update_at": "2025-05-05T04:49:12.991479", "home_team": "Hartlepool", "competition_name": "National League", "away_team": "Forest Green", "market": "classic", "competition_cluster": "England", "prediction": "1X", "status": "pending", "federation": "UEFA", "is_expired": false, "odds": {"1": 2.825, "X": 3.267, "2": 2.228, "1X": 1.558, "X2": 1.367, "12": 1.292}}, {"season": "2024 - 2025", "id": 353900, "result": "", "start_date": "2025-05-05T15:00:00", "last_update_at": "2025-05-05T04:49:12.991479", "home_team": "Oldham", "competition_name": "National League", "away_team": "Ebbsfleet United", "market": "classic", "competition_cluster": "England", "prediction": "1", "status": "pending", "federation": "UEFA", "is_expired": false, "odds": {"1": 1.322, "X": 4.442, "2": 8.55, "1X": 1.05, "X2": 3.103, "12": 1.168}}, {"season": "2024 - 2025", "id": 353901, "result": "", "start_date": "2025-05-05T15:00:00", "last_update_at": "2025-05-05T04:49:12.991479", "home_team": "Solihull Moors", "competition_name": "National League", "away_team": "Dagenham and Redbridge", "market": "classic", "competition_cluster": "England", "prediction": "2", "status": "pending", "federation": "UEFA", "is_expired": false, "odds": {"1": 3.895, "X": 3.423, "2": 1.807, "1X": 1.907, "X2": 1.207, "12": 1.27}}, {"season": "2025", "id": 353924, "result": "", "start_date": "2025-05-05T19:45:00", "last_update_at": "2025-05-05T04:49:12.991479", "home_team": "Derry City", "competition_name": "Premier Division", "away_team": "St Patrick's Athletic", "market": "classic", "competition_cluster": "Ireland", "prediction": "1X", "status": "pending", "federation": "UEFA", "is_expired": false, "odds": {"1": 2.26, "X": 3.073, "2": 3.217, "1X": 1.32, "X2": 1.585, "12": 1.35}}, {"season": "2025", "id": 353929, "result": "", "start_date": "2025-05-05T12:00:00", "last_update_at": "2025-05-05T08:49:42.444686", "home_team": "FS Jelgava", "competition_name": "Virsliga", "away_team": "RFS Riga", "market": "classic", "competition_cluster": "Latvia", "prediction": "2", "status": "pending", "federation": "UEFA", "is_expired": false, "odds": {"1": 8.81, "X": 5.18, "2": 1.248, "1X": 3.422, "X2": 1.045, "12": 1.117}}, {"season": "2024 - 2025", "id": 353908, "result": "", "start_date": "2025-05-05T16:00:00", "last_update_at": "2025-05-05T08:49:42.444686", "home_team": "Spartak Pleven", "competition_name": "Second PFL", "away_team": "Botev Plovdiv II", "market": "classic", "competition_cluster": "Bulgaria", "prediction": "1", "status": "pending", "federation": "UEFA", "is_expired": false, "odds": {"1": 1.62, "X": 3.63, "2": 4.777, "1X": 1.12, "X2": 2.02, "12": 1.205}}, {"season": "2025", "id": 353922, "result": "", "start_date": "2025-05-05T17:00:00", "last_update_at": "2025-05-05T08:49:42.444686", "home_team": "Shelbourne", "competition_name": "Premier Division", "away_team": "Waterford", "market": "classic", "competition_cluster": "Ireland", "prediction": "1", "status": "pending", "federation": "UEFA", "is_expired": false, "odds": {"1": 1.587, "X": 3.717, "2": 5.867, "1X": 1.123, "X2": 2.295, "12": 1.258}}, {"season": "2024 - 2025", "id": 353947, "result": "", "start_date": "2025-05-05T18:00:00", "last_update_at": "2025-05-05T08:49:42.444686", "home_team": "Kasimpasa", "competition_name": "Super Lig", "away_team": "Trabzonspor", "market": "classic", "competition_cluster": "Turkey", "prediction": "1X", "status": "pending", "federation": "UEFA", "is_expired": false, "odds": {"1": 2.345, "X": 3.655, "2": 2.682, "1X": 1.438, "X2": 1.557, "12": 1.265}}, {"season": "2024 - 2025", "id": 353897, "result": "", "start_date": "2025-05-05T15:00:00", "last_update_at": "2025-05-05T08:49:42.444686", "home_team": "Gateshead", "competition_name": "National League", "away_team": "Southend", "market": "classic", "competition_cluster": "England", "prediction": "12", "status": "pending", "federation": "UEFA", "is_expired": false, "odds": {"1": 2.562, "X": 3.383, "2": 2.38, "1X": 1.502, "X2": 1.442, "12": 1.268}}, {"season": "2025", "id": 353701, "result": "", "start_date": "2025-05-05T21:05:00", "last_update_at": "2025-05-05T08:49:42.444686", "home_team": "Nueva Chicago", "competition_name": "Primera Nacional", "away_team": "Estudiantes Buenos Aires", "market": "classic", "competition_cluster": "Argentina", "prediction": "1X", "status": "pending", "federation": "CONMEBOL", "is_expired": false, "odds": {"1": 2.465, "X": 2.803, "2": 3.072, "1X": 1.338, "X2": 1.494, "12": 1.384}}, {"season": "2024 - 2025", "id": 353905, "result": "", "start_date": "2025-05-05T20:00:00", "last_update_at": "2025-05-05T08:49:42.444686", "home_team": "Girona", "competition_name": "Primera Division", "away_team": "Mallorca", "market": "classic", "competition_cluster": "Spain", "prediction": "1X", "status": "pending", "federation": "UEFA", "is_expired": false, "odds": {"1": 2.022, "X": 3.173, "2": 4.17, "1X": 1.222, "X2": 1.775, "12": 1.35}}, {"season": "2024 - 2025", "id": 353980, "result": "", "start_date": "2025-05-05T17:45:00", "last_update_at": "2025-05-05T08:49:42.444686", "home_team": "Ajman Club", "competition_name": "Pro-League", "away_team": "Al Urooba Club", "market": "classic", "competition_cluster": "UAE", "prediction": "1", "status": "pending", "federation": "AFC", "is_expired": false, "odds": {"1": 1.727, "X": 3.678, "2": 3.965, "1X": 1.213, "X2": 1.897, "12": 1.243}}, {"season": "2024 - 2025", "id": 353891, "result": "", "start_date": "2025-05-05T20:00:00", "last_update_at": "2025-05-05T08:49:42.444686", "home_team": "Crystal Palace", "competition_name": "Premier League", "away_team": "Nottingham", "market": "classic", "competition_cluster": "England", "prediction": "12", "status": "pending", "federation": "UEFA", "is_expired": false, "odds": {"1": 2.178, "X": 3.41, "2": 3.357, "1X": 1.306, "X2": 1.666, "12": 1.306}}, {"season": "2025", "id": 353954, "result": "", "start_date": "2025-05-05T12:00:00", "last_update_at": "2025-05-05T08:49:42.444686", "home_team": "Henan FC", "competition_name": "Super League", "away_team": "Tianjin Jinmen Tiger", "market": "classic", "competition_cluster": "China", "prediction": "12", "status": "pending", "federation": "AFC", "is_expired": false, "odds": {"1": 1.973, "X": 3.582, "2": 3.47, "1X": 1.282, "X2": 1.753, "12": 1.27}}, {"season": "2025", "id": 353942, "result": "", "start_date": "2025-05-05T18:10:00", "last_update_at": "2025-05-05T08:49:42.444686", "home_team": "Elfsborg", "competition_name": "Allsvenskan", "away_team": "GAIS Goteborg", "market": "classic", "competition_cluster": "Sweden", "prediction": "12", "status": "pending", "federation": "UEFA", "is_expired": false, "odds": {"1": 1.953, "X": 3.53, "2": 3.69, "1X": 1.252, "X2": 1.817, "12": 1.285}}, {"season": "2025", "id": 353944, "result": "", "start_date": "2025-05-05T18:00:00", "last_update_at": "2025-05-05T08:49:42.444686", "home_team": "Orebro", "competition_name": "Superettan", "away_team": "Trelleborgs", "market": "classic", "competition_cluster": "Sweden", "prediction": "1X", "status": "pending", "federation": "UEFA", "is_expired": false, "odds": {"1": 2.503, "X": 3.395, "2": 2.557, "1X": 1.47, "X2": 1.485, "12": 1.29}}, {"season": "2025", "id": 353941, "result": "", "start_date": "2025-05-05T18:00:00", "last_update_at": "2025-05-05T08:49:42.444686", "home_team": "Malmo", "competition_name": "Allsvenskan", "away_team": "Brommapojkarna", "market": "classic", "competition_cluster": "Sweden", "prediction": "1", "status": "pending", "federation": "UEFA", "is_expired": false, "odds": {"1": 1.408, "X": 4.767, "2": 6.992, "1X": 1.09, "X2": 2.788, "12": 1.17}}, {"season": "2025", "id": 353873, "result": "", "start_date": "2025-05-05T21:05:00", "last_update_at": "2025-05-05T08:49:42.444686", "home_team": "Nueva Chicago", "competition_name": "Primera Nacional", "away_team": "Estudiantes Buenos Aires", "market": "classic", "competition_cluster": "Argentina", "prediction": "12", "status": "pending", "federation": "CONMEBOL", "is_expired": false, "odds": {"1": 2.465, "X": 2.803, "2": 3.072, "1X": 1.338, "X2": 1.494, "12": 1.384}}, {"season": "2024 - 2025", "id": 353906, "result": "", "start_date": "2025-05-05T19:30:00", "last_update_at": "2025-05-05T08:49:42.444686", "home_team": "Castellon", "competition_name": "Segunda Division", "away_team": "Sporting Gijon", "market": "classic", "competition_cluster": "Spain", "prediction": "1X", "status": "pending", "federation": "UEFA", "is_expired": false, "odds": {"1": 1.808, "X": 3.583, "2": 3.967, "1X": 1.215, "X2": 1.915, "12": 1.265}}, {"season": "2024 - 2025", "id": 353893, "result": "", "start_date": "2025-05-05T15:00:00", "last_update_at": "2025-05-05T08:49:42.444686", "home_team": "Altrincham", "competition_name": "National League", "away_team": "Tamworth", "market": "classic", "competition_cluster": "England", "prediction": "1X", "status": "pending", "federation": "UEFA", "is_expired": false, "odds": {"1": 1.94, "X": 3.628, "2": 3.207, "1X": 1.298, "X2": 1.74, "12": 1.24}}, {"season": "2024 - 2025", "id": 353894, "result": "", "start_date": "2025-05-05T15:00:00", "last_update_at": "2025-05-05T08:49:42.444686", "home_team": "Braintree", "competition_name": "National League", "away_team": "Rochdale", "market": "classic", "competition_cluster": "England", "prediction": "2", "status": "pending", "federation": "UEFA", "is_expired": false, "odds": {"1": 3.943, "X": 3.47, "2": 1.787, "1X": 1.95, "X2": 1.198, "12": 1.264}}, {"season": "2024 - 2025", "id": 353983, "result": "", "start_date": "2025-05-05T11:00:00", "last_update_at": "2025-05-05T08:49:42.444686", "home_team": "Quang Nam", "competition_name": "V.League 1", "away_team": "Cong An Ha Noi", "market": "classic", "competition_cluster": "Vietnam", "prediction": "2", "status": "pending", "federation": "AFC", "is_expired": false, "odds": {"1": 3.835, "X": 3.332, "2": 1.82, "1X": 1.837, "X2": 1.197, "12": 1.25}}, {"season": "2024 - 2025", "id": 353909, "result": "", "start_date": "2025-05-05T16:30:00", "last_update_at": "2025-05-05T08:49:42.444686", "home_team": "Pirin Blagoevgrad", "competition_name": "Second PFL", "away_team": "Yantra Gabrovo", "market": "classic", "competition_cluster": "Bulgaria", "prediction": "1", "status": "pending", "federation": "UEFA", "is_expired": false, "odds": {"1": 1.59, "X": 3.663, "2": 4.87, "1X": 1.105, "X2": 2.13, "12": 1.195}}, {"season": "2024 - 2025", "id": 353925, "result": "", "start_date": "2025-05-05T18:30:00", "last_update_at": "2025-05-05T08:49:42.444686", "home_team": "Maccabi Tel Aviv", "competition_name": "Championship Group", "away_team": "Hapoel Beer Sheva", "market": "classic", "competition_cluster": "Israel", "prediction": "12", "status": "pending", "federation": "UEFA", "is_expired": false, "odds": {"1": 2.215, "X": 3.378, "2": 2.848, "1X": 1.348, "X2": 1.592, "12": 1.29}}, {"season": "2025", "id": 353957, "result": "", "start_date": "2025-05-05T12:35:00", "last_update_at": "2025-05-05T08:49:42.444686", "home_team": "Qingdao Hainiu", "competition_name": "Super League", "away_team": "Changchun Yatai", "market": "classic", "competition_cluster": "China", "prediction": "1X", "status": "pending", "federation": "AFC", "is_expired": false, "odds": {"1": 2.31, "X": 3.467, "2": 2.892, "1X": 1.385, "X2": 1.57, "12": 1.282}}, {"season": "2024 - 2025", "id": 353904, "result": "", "start_date": "2025-05-05T19:45:00", "last_update_at": "2025-05-05T08:49:42.444686", "home_team": "Genoa", "competition_name": "Serie A", "away_team": "Milan", "market": "classic", "competition_cluster": "Italy", "prediction": "2", "status": "pending", "federation": "UEFA", "is_expired": false, "odds": {"1": 4.548, "X": 3.718, "2": 1.788, "1X": 1.998, "X2": 1.185, "12": 1.268}}, {"season": "2024 - 2025", "id": 353896, "result": "", "start_date": "2025-05-05T15:00:00", "last_update_at": "2025-05-05T08:49:42.444686", "home_team": "Fylde", "competition_name": "National League", "away_team": "Barnet", "market": "classic", "competition_cluster": "England", "prediction": "2", "status": "pending", "federation": "UEFA", "is_expired": false, "odds": {"1": 8.483, "X": 5.067, "2": 1.267, "1X": 3.383, "X2": 1.05, "12": 1.137}}]}
